Workbook

Sheet  Green Zebra Historic Data
A1: Collected from Exhibits 5, and 6
A2: Income statement
B3: Item | C3: 2017 | D3: 2018 | E3: 2019e | K3: Collected from Exhibits 5, and 6 | M3: Number of Stores | N3: 3 | O3: 32 | P3: 33
B4: Sales | C4: 10006049 | D4: 10782087 | E4: 12683289 | K4: Income statement
B5: Cost of Sales (COGS) | C5: 6329714 | D5: 6697427 | E5: 7765068
B6: Gross Profit | C6: 3676335 | D6: 4084660 | E6: 4918221 | N6: 2017 | O6: 2018 | P6: 2019e 1
B7: Store-Level Operating Exp | C7: 3799791 | D7: 3858400 | E7: 4355039 | M7: Sales | N7: 10006049 | O7: 10782087 | P7: 12683289
B8: Corporate-Level Operating Exp | C8: 1254048 | D8: 1303468 | E8: 1486581 | M8: Cost of Sales | N8: 6329714 | O8: 6697427 | P8: 7765068
B9: EBITDA | C9: -1377504 | D9: -1077208 | E9: -923398 | G9: Gross Margin | H9: =C6/C4 -> 0.36741125 | I9: =D6/D4 -> 0.3788376 | J9: =E6/E4 -> 0.38777174 | M9: Gross Profit | N9: 3676335 | O9: 4084660 | P9: 4918221
B10: Depreciation | C10: 301100 | D10: 312080 | E10: 355322 | G10: Store-Level Operating Expense | H10: =C7/C4 -> 0.37974939 | I10: =D7/D4 -> 0.3578528 | J10: =E7/E4 -> 0.34336827
B11: Interest Expense | C11: 555022 | D11: 452291 | E11: 433114 | G11: Corporate Overhead | H11: =C8/C4 -> 0.12532899 | I11: =D8/D4 -> 0.12089199 | J11: =E8/E4 -> 0.11720785 | M11: Payroll & Benefits | N11: 3009276 | O11: 3109118 | P11: 3576002
B12: Net Income (Loss) | C12: -2244877 | D12: -1857000 | E12: -1727962 | G12: EBITDA Margin | H12: =C9/C4 -> -0.13766713 | I12: =D9/D4 -> -0.099907189 | J12: =E9/E4 -> -0.072804302 | M12: Advertising & Marketing | N12: 139333 | O12: 183958 | P12: 192668
G13: Net Profit Margin | H13: =C12/C4 -> -0.22435199 | I13: =D12/D4 -> -0.17223011 | J13: =E12/E4 -> -0.13623927 | M13: Occupancy & Other | N13: 1905230 | O13: 1868793 | P13: 2072950
G14: Current Ratio | H14: =C26/C34 -> 0.89280148 | I14: =D26/D34 -> 0.69594279 | J14: =E26/E34 -> 1.0766293 | M14: Total - Other Operating Expenses | N14: 5053839 | O14: 5161868 | P14: 5841619
B15: EBIT | E15: =E9+E11 -> -490284 | G15: Debt to Equity | H15: =C41/C37 -> 0.57800575 | I15: =D41/D37 -> 0.56604579 | J15: =E41/E37 -> 0.58780549
M16: EBITDA | N16: -1377504 | O16: -1077208 | P16: -923398
M18: Depreciation/Amortization | N18: 301100 | O18: 312080 | P18: 355322
M19: Interest Expense/(Income) | N19: 555022 | O19: 452291 | P19: 433114
B20: Balance Sheet | C20: 2017 | D20: 2018 | E20: 2019e
B21: Assets | M21: Income before Fed Income Tax | N21: -2233625 | O21: -1841579 | P21: -1711834
B22: Cash & Equivalents | C22: 271249 | D22: 376420 | E22: 991610 | G22: =G25*G27+
B23: Receivables | C23: 19377 | D23: 75496 | E23: 65000 | M23: Income Tax2 | N23: 11252 | O23: 15421 | P23: 16129
B24: Inventory | C24: 441123 | D24: 489220 | E24: 558779
B25: Other Current Assets | C25: 205339 | D25: 23717 | E25: 25000 | M25: Net Income/(Loss) | N25: -2244877 | O25: -1857000 | P25: -1727962
B26: Total Current Assets | C26: 937088 | D26: 964853 | E26: 1640389 | K26: Collected from Exhibits 5, and 6
B27: Net Long-Term Assets | C27: 3213085 | D27: 3097801 | E27: 3751686 | K27: Balance sheet
B28: Total Assets | C28: 4150173 | D28: 4062654 | E28: 5392075
M29: Column1 | N29: Column2 | O29: Column3 | P29: Column4
B30: Liabilities & Equity | M30: Cash & Equivalents | N30: 271249 | O30: 376420 | P30: 991610
B31: Accounts Payable | C31: 428128 | D31: 627075 | E31: 596550 | G31: =G30*60% + | M31: Receivables | N31: 19377 | O31: 75496 | P31: 65000
B32: Other Current Liabilities | C32: 521476 | D32: 684363 | E32: 892828 | M32: Inventory | N32: 441123 | O32: 489220 | P32: 558779
B33: Line of Credit | C33: 100000 | D33: 74959 | E33: 34256 | M33: Other Current Assets | N33: 205339 | O33: 23717 | P33: 25000
B34: Total Current Liabilities | C34: 1049604 | D34: 1386397 | E34: 1523634 | M34: Total Current Assets | N34: 937085 | O34: 964854 | P34: 1640389
B35: Long-Term Debt & LT Liabilities | C35: 4660101 | D35: 6095693 | E35: 7019863 | M35: Total LT Assets2 | N35: 3213085 | O35: 3097801 | P35: 3751686
B36: Total Liabilities | C36: 5709705 | D36: 7482090 | E36: 8543497 | M36: Total Assets | N36: 4150171 | O36: 4062655 | P36: 5392075
B37: Stockholder’s Equity | C37: 7180157 | D37: 7177255 | E37: 9173230
B38: Retained Earnings | C38: -6494813 | D38: -8739690 | E38: -10596690 | M38: LIABILITIES
B39: Current Year Earnings | C39: -2244877 | D39: -1857000 | E39: -1727962 | M39: Accounts Payable | N39: 428128 | O39: 627075 | P39: 596550
B40: Total Equity | C40: -1559533 | D40: -3419435 | E40: -3151422 | M40: Other Current Liabilities | N40: 521476 | O40: 684363 | P40: 892828
B41: Total Liab. & Equity | C41: 4150172 | D41: 4062655 | E41: 5392075 | M41: Line of Credit | N41: 100000 | O41: 74959 | P41: 34256
M42: Total Current Liabilities | N42: 1049604 | O42: 1386397 | P42: 1523634
M44: Long Term Debt & LT Liabilities2 | N44: 4660101 | O44: 6095693 | P44: 7019863
M45: Total Liabilities | N45: 5709705 | O45: 7482089 | P45: 8543497
M47: NET WORTH
M48: Stockholder's Equity | N48: 7180157 | O48: 7177255 | P48: 9173230
M49: Retained Earnings | N49: -6494813 | O49: -8739690 | P49: -10596690
M50: Current Year Earnings | N50: -2244877 | O50: -1857000 | P50: -1727962
M51: Total Net Worth | N51: -1559532 | O51: -3419435 | P51: -3151422
M52: Total Liabilities & Net Worth | N52: 4150173 | O52: 4062654 | P52: 5392075
B56: b
L64: Column1 | M64: Column2 | N64: Column3 | O64: Column4 | P64: Column5 | Q64: Column6 | R64: Column7 | S64: Column8
L65: Existing 3-store Operation (3 stores) | M65: 2019e | N65: 2020 | O65: 2021 | P65: 2022 | Q65: 2023 | R65: 2024 | S65: 2025
L66: Sales | N66: 12355557 | O66: 13041944 | P66: 13642033 | Q66: 14083972 | R66: 14095972 | S66: 14095972
L67: EBITDA External Financing | N67: -359449 | O67: -77149 | P67: 82446 | Q67: 189587 | R67: 154820 | S67: 103164
L68: Needed | M68: 578999 | N68: 61929 | O68: -199826 | P68: -282508 | Q68: -372990 | R68: -321643 | S68: -211115
L70: Column1 | M70: Column2 | N70: Column3 | O70: Column4 | P70: Column5 | Q70: Column6 | R70: Column7
L71: Investment Related | M71: 2020 | N71: 2021 | O71: 2022 | P71: 2023 | Q71: 2024 | R71: 2025
L72: Fixed assets, net (% of sales)1 | M72: 0.187 | N72: 0.153 | O72: 0.128 | P72: 0.108 | Q72: 0.095 | R72: 0.089
L73: Depreciation | M73: 420072 | N73: 402711 | O73: 326661 | P73: 311583 | Q73: 263919 | R73: 125551
L75: Column1 | M75: Column2 | N75: Column3 | O75: Column4
L76: Income Statement2 | M76: % of: | N76: 2020 | O76: After 2020:
L77: Sales growth rate | N77: 35 | O77: 7.0%, 5.0%, 4.0%, then steady state at 1.0%
L78: Cost of goods sold | M78: of sales | N78: 5.95 | O78: leveling off at 58% by 2022
L79: Payroll & Benefits | M79: of sales | N79: 2.53 | O79: falling to 24.0% by 2022
L80: Occupancy & other | M80: of sales | N80: 1.4 | O80: falling to 12.3% by 2024
L81: Advertising & Marketing | M81: of sales | N81: 0.1 | O81: constant
L82: Balance Sheet
L83: Cash & Equivalents | M83: % of sales | N83: 0.2 | O83: constant
L84: Inventories | M84: % cost of good sold | N84: 0.63 | O84: constant
L85: Accounts payable | M85: % cost of good sold | N85: 0.7 | O85: constant
L86: Other current liabilities | M86: of sales | N86: 0.19 | O86: constant
L93: Name | M93: 2020 | N93: 2021 | O93: 2022 | P93: 2023 | Q93: 2024 | R93: 2025
L94: Sales | M94: =N66 -> 12355557 | N94: =O66 -> 13041944 | O94: =P66 -> 13642033 | P94: =Q66 -> 14083972 | Q94: =R66 -> 14095972 | R94: =S66 -> 14095972
L95: Growth (%) | M95: – | N95: 0.07 | O95: 0.05 | P95: 0.04 | Q95: 0.02 | R95: 0.01
L96: COGS (% of Sales) | M96: 0.595 | N96: 0.59 | O96: 0.58 | P96: 0.58 | Q96: 0.58 | R96: 0.58
L97: COGS | M97: =M94*M96 -> 7351556.4 | N97: =N94*N96 -> 7694747 | O97: =O94*O96 -> 7912379.1 | P97: =P94*P96 -> 8168703.8 | Q97: =Q94*Q96 -> 8175663.8 | R97: =R94*R96 -> 8175663.8
L98: Gross Profit | M98: =M94-(M94*M96) -> 5004000.6 | N98: =N94-(N94*N96) -> 5347197 | O98: =O94-(O94*O96) -> 5729653.9 | P98: =P94-(P94*P96) -> 5915268.2 | Q98: =Q94-(Q94*Q96) -> 5920308.2 | R98: =R94-(R94*R96) -> 5920308.2
L99: Payroll & Benefits (%) | M99: 0.253 | N99: 0.25 | O99: 0.245 | P99: 0.242 | Q99: 0.24 | R99: 0.24
L100: Payroll & Benefits | M100: =M94*M99 -> 3125955.9 | N100: =N94*N99 -> 3260486 | O100: =O94*O99 -> 3342298.1 | P100: =P94*P99 -> 3408321.2 | Q100: =Q94*Q99 -> 3383033.3 | R100: =R94*R99 -> 3383033.3
L101: Occupancy & Other (%) | M101: 0.14 | N101: 0.135 | O101: 0.13 | P101: 0.125 | Q101: 0.123 | R101: 0.123
L102: Occupancy & Other | M102: =M94*M101 -> 1729778 | N102: =N94*N101 -> 1760662.4 | O102: =O94*O101 -> 1773464.3 | P102: =P94*P101 -> 1760496.5 | Q102: =Q94*Q101 -> 1733804.6 | R102: =R94*R101 -> 1733804.6
L103: Advertising (1% of Sales) | M103: =1%*M94 -> 123555.57 | N103: =1%*N94 -> 130419.44 | O103: =1%*O94 -> 136420.33 | P103: =1%*P94 -> 140839.72 | Q103: =1%*Q94 -> 140959.72 | R103: =1%*R94 -> 140959.72
L104: EBITDA | M104: =M98-(M100+M102+M103) -> 24711.114 | N104: =N98-(N100+N102+N103) -> 195629.16 | O104: =O98-(O100+O102+O103) -> 477471.16 | P104: =P98-(P100+P102+P103) -> 605610.8 | Q104: =Q98-(Q100+Q102+Q103) -> 662510.68 | R104: =R98-(R100+R102+R103) -> 662510.68
L105: Depreciation | M105: 420072 | N105: 402711 | O105: 326661 | P105: 311583 | Q105: 262919 | R105: 125551
L106: EBIT | M106: =M104-M105 -> -395360.89 | N106: =N104-N105 -> -207081.84 | O106: =O104-O105 -> 150810.16 | P106: =P104-P105 -> 294027.8 | Q106: =Q104-Q105 -> 399591.68 | R106: =R104-R105 -> 536959.68
L107: Interest | M107: 170000 | N107: 170000 | O107: 170000 | P107: 170000 | Q107: 170000 | R107: 170000
L108: Income before tax | M108: =M106-M107 -> -565360.89 | N108: =N106-N107 -> -377081.84 | O108: =O106-O107 -> -19189.845 | P108: =P106-P107 -> 124027.8 | Q108: =Q106-Q107 -> 229591.68 | R108: =R106-R107 -> 366959.68
L109: Fixed State Tax | M109: 15000 | N109: =Table518[[#This Row],[2020]] -> 15000 | O109: =Table518[[#This Row],[2021]] -> 15000 | P109: =Table518[[#This Row],[2022]] -> 15000 | Q109: =Table518[[#This Row],[2023]] -> 15000 | R109: =Table518[[#This Row],[2024]] -> 15000
L110: Net Income | M110: =M108-M109 -> -580360.89 | N110: =N108-N109 -> -392081.84 | O110: =O108-O109 -> -34189.845 | P110: =P108-P109 -> 109027.8 | Q110: =Q108-Q109 -> 214591.68 | R110: =R108-R109 -> 351959.68

Sheet Finance option
B5: Choice | C5: Condition | D5: Benefit | E5: Problem
B6: 1) Bridge Loan | C6: $2.2M principal, 180k 1st day payment, 12.5% interest (6.25% cash + 6.25% PIK), due 12–18 months | D6: Quick, no equity dilution | E6: High interest, balloon maturity, 180k upfront fee
B7: 2) 12M venture capital | C7: 12M equity, 2 new board seats, big dilution, used for 3+ store Seattle expansion | D7: Large capital for multi-store expansion | E7: Big dilution, loss of control
B8: 3) Mixed | C8: $2–3M total ($1.5–2.5M equity + $0.5–1M equip loan @ 11.5%), uncertain availability | D8: less interest than bridge keep more control compare to 12m vc | E8: CFO sees it as unlikely; multiple negotiations; smaller scale

Sheet 1-Store Portland Expansion
R2: Fixed asset of sale % | S2: 0.187 | T2: 0.153 | U2: 0.128 | V2: 0.108 | W2: 0.095 | X2: 0.089 | Y2: Exhibihit7 forecast 3
B3: 1-Store Portland Expansion | C3: 920000
F4: Income Statement FC20-25 without new debt | N4: Cash Flow Statement | W4: Balance Sheet:
W5: Item | X5: 2020 | Y5: 2021 | Z5: 2022 | AA5: 2023 | AB5: 2024 | AC5: 2025
F6: Name | G6: 2020 | H6: 2021 | I6: 2022 | J6: 2023 | K6: 2024 | L6: 2025 | N6: Item | O6: 2020 | P6: 2021 | Q6: 2022 | R6: 2023 | S6: 2024 | T6: 2025 | W6: Assets
B7: Total up front cost is | C7: =SUM(C3:C5) -> 920000 | D7: needed | F7: Sales | G7: 17100000 | H7: =Table5[[#This Row],[2020]]+(Table5[[#This Row],[2020]]*H8) -> 18297000 | I7: =Table5[[#This Row],[2021]]+(Table5[[#This Row],[2021]]*I8) -> 19211850 | J7: =Table5[[#This Row],[2022]]+(Table5[[#This Row],[2022]]*J8) -> 19980324 | K7: =Table5[[#This Row],[2023]]+(Table5[[#This Row],[2023]]*K8) -> 20379930 | L7: =Table5[[#This Row],[2024]]+(Table5[[#This Row],[2024]]*L8) -> 20583730 | N7: Net Income | O7: =G23 -> -570872 | P7: =H23 -> -313256 | Q7: =I23 -> 160753.75 | R7: =J23 -> 362570.93 | S7: =K23 -> 509937.73 | T7: =L23 -> 656884.3 | W7: - Cash & Equivalents | X7: =Table5[[#This Row],[2020]]*2% -> 342000 | Y7: =Table5[[#This Row],[2021]]*2% -> 365940 | Z7: =Table5[[#This Row],[2022]]*2% -> 384237 | AA7: =Table5[[#This Row],[2023]]*2% -> 399606.48 | AB7: =Table5[[#This Row],[2024]]*2% -> 407598.61 | AC7: =Table5[[#This Row],[2025]]*2% -> 411674.6
D8: interest rate | E8: 0.125 | F8: Growth (%) | G8: – | H8: 0.07 | I8: 0.05 | J8: 0.04 | K8: 0.02 | L8: 0.01 | N8: Adjustments for: | W8: - Inventory | X8: =G10*6.3% -> 640993.5 | Y8: =H10*6.3% -> 680099.49 | Z8: =I10*6.3% -> 702001 | AA8: =J10*6.3% -> 730081.04 | AB8: =K10*6.3% -> 744682.66 | AC8: =L10*6.3% -> 752129.49
F9: COGS (% of Sales) | G9: 0.595 | H9: 0.59 | I9: 0.58 | J9: 0.58 | K9: 0.58 | L9: 0.58 | N9: - Depreciation | O9: =G18 -> 420072 | P9: =H18 -> 402711 | Q9: =I18 -> 326661 | R9: =J18 -> 311583 | S9: =K18 -> 262919 | T9: =L18 -> 125551 | W9: - Other Current Assets | X9: =X33 -> 25000 | Y9: =Y33 -> 25000 | Z9: =Z33 -> 25000 | AA9: =AA33 -> 25000 | AB9: =AB33 -> 25000 | AC9: =AC33 -> 25000 | AD9: 250000 taken from 2019 BS and no information about change in future.
F10: COGS | G10: =G7*G9 -> 10174500 | H10: =H7*H9 -> 10795230 | I10: =I7*I9 -> 11142873 | J10: =J7*J9 -> 11588588 | K10: =K7*K9 -> 11820360 | L10: =L7*L9 -> 11938563 | N10: Changes in Working Capital: | W10: Total Current Assets | X10: =SUM(X7:X9) -> 1007993.5 | Y10: =SUM(Y7:Y9) -> 1071039.5 | Z10: =SUM(Z7:Z9) -> 1111238 | AA10: =SUM(AA7:AA9) -> 1154687.5 | AB10: =SUM(AB7:AB9) -> 1177281.3 | AC10: =SUM(AC7:AC9) -> 1188804.1
A11: Other given data | F11: Gross Profit | G11: =G7-(G7*G9) -> 6925500 | H11: =H7-(H7*H9) -> 7501770 | I11: =I7-(I7*I9) -> 8068977 | J11: =J7-(J7*J9) -> 8391736.1 | K11: =K7-(K7*K9) -> 8559570.8 | L11: =L7-(L7*L9) -> 8645166.5 | N11: - Inventories | O11: =X8 -> 640993.5 | P11: =Y8 -> 680099.49 | Q11: =Z8 -> 702001 | R11: =AA8 -> 730081.04 | S11: =AB8 -> 744682.66 | T11: =AC8 -> 752129.49 | U11: Exihibit 7 - 6.3% of cogs | W11: - Fixed Assets (net) | X11: =G7*S2 -> 3197700 | Y11: =H7*T2 -> 2799441 | Z11: =I7*U2 -> 2459116.8 | AA11: =J7*V2 -> 2157875 | AB11: =K7*W2 -> 1936093.4 | AC11: =L7*X2 -> 1831952 | AD11: last year fixed assent from exibit 6 minus depeciation value we calculated
B12: Item | C12: Value / Rate | F12: Payroll & Benefits (%) | G12: 0.253 | H12: 0.25 | I12: 0.245 | J12: 0.242 | K12: 0.24 | L12: 0.24 | N12: + Accounts Payable | O12: =G10*7% -> 712215 | P12: =H10*7% -> 755666.1 | Q12: =I10*7% -> 780001.11 | R12: =J10*7% -> 811201.15 | S12: =K10*7% -> 827425.18 | T12: =L10*7% -> 835699.43 | U12: Exihibit 7 - 7% of cogs | W12: Total Assets | X12: =SUM(X9:X11) -> 4230693.5 | Y12: =SUM(Y9:Y11) -> 3895480.5 | Z12: =SUM(Z9:Z11) -> 3595354.8 | AA12: =SUM(AA9:AA11) -> 3337562.5 | AB12: =SUM(AB9:AB11) -> 3138374.7 | AC12: =SUM(AC9:AC11) -> 3045756
B13: 2020 Sales (4 total stores) | C13: 17100000 | F13: Payroll & Benefits | G13: =G7*G12 -> 4326300 | H13: =H7*H12 -> 4574250 | I13: =I7*I12 -> 4706903.2 | J13: =J7*J12 -> 4835238.4 | K13: =K7*K12 -> 4891183.3 | L13: =L7*L12 -> 4940095.1 | N13: Cash from Operations | O13: =O7+O9-O11+O12 -> -79578.5 | P13: =P7+P9-P11+P12 -> 165021.61 | Q13: =Q7+Q9-Q11+Q12 -> 565414.86 | R13: =R7+R9-R11+R12 -> 755274.05 | S13: =S7+S9-S11+S12 -> 855599.25 | T13: =T7+T9-T11+T12 -> 866005.24 | W13: Liabilities
B14: Sales Growth (2021–2025) | C14: 20400 BY 2024 (7,5,4,2) and 1% after | F14: Occupancy & Other (%) | G14: 0.14 | H14: 0.135 | I14: 0.13 | J14: 0.125 | K14: 0.123 | L14: 0.123 | N14: Cash from Investing: | W14: - Accounts Payable | X14: =G10*7% -> 712215 | Y14: =H10*7% -> 755666.1 | Z14: =I10*7% -> 780001.11 | AA14: =J10*7% -> 811201.15 | AB14: =K10*7% -> 827425.18 | AC14: =L10*7% -> 835699.43
B15: COGS (% Sales) | C15: 59.5% in 2020, gradually down to 58% by 2022 | F15: Occupancy & Other | G15: =G7*G14 -> 2394000 | H15: =H7*H14 -> 2470095 | I15: =I7*I14 -> 2497540.5 | J15: =J7*J14 -> 2497540.5 | K15: =K7*K14 -> 2506731.4 | L15: =L7*L14 -> 2531798.8 | N15: CapEx for New Store | O15: =-C7 -> -920000 | P15: 0 | Q15: 0 | R15: 0 | S15: 0 | T15: 0 | W15: - Other Current Liabilities | X15: =G7*1.9% -> 324900 | Y15: =H7*1.9% -> 347643 | Z15: =I7*1.9% -> 365025.15 | AA15: =J7*1.9% -> 379626.16 | AB15: =K7*1.9% -> 387218.68 | AC15: =L7*1.9% -> 391090.87
B16: Payroll & Benefits | C16: 25.3% in 2020, down to 24% by 2022 (of sale) | F16: Advertising (1% of Sales) | G16: =1%*G7 -> 171000 | H16: =1%*H7 -> 182970 | I16: =1%*I7 -> 192118.5 | J16: =1%*J7 -> 199803.24 | K16: =1%*K7 -> 203799.3 | L16: =1%*L7 -> 205837.3 | N16: Cash from Financing: | W16: - Line of Credit | X16: 45000 | Y16: 45000 | Z16: 45000 | AA16: 45000 | AB16: 45000 | AC16: 45000
B17: Occupancy & Other | C17: 14% in 2020, 12.3% by 2024 | F17: EBITDA | G17: =G11-(G13+G15+G16) -> 34200 | H17: =H11-(H13+H15+H16) -> 274455 | I17: =I11-(I13+I15+I16) -> 672414.75 | J17: =J11-(J13+J15+J16) -> 859153.93 | K17: =K11-(K13+K15+K16) -> 957856.73 | L17: =L11-(L13+L15+L16) -> 967435.3 | N17: - New Debt | O17: 0 | P17: 0 | Q17: 0 | R17: 0 | S17: 0 | T17: 0 | W17: Total Current Liabilities | X17: =SUM(X13:X16) -> 1082115 | Y17: =SUM(Y13:Y16) -> 1148309.1 | Z17: =SUM(Z13:Z16) -> 1190026.3 | AA17: =SUM(AA13:AA16) -> 1235827.3 | AB17: =SUM(AB13:AB16) -> 1259643.9 | AC17: =SUM(AC13:AC16) -> 1271790.3
B18: Advertising & Marketing | C18: 1% of Sales | F18: Depreciation | G18: 420072 | H18: 402711 | I18: 326661 | J18: 311583 | K18: 262919 | L18: 125551 | N18: - Debt Repayment (no information about old debt repayment found.) | O18: 0 | P18: 0 | Q18: 0 | R18: 0 | S18: 0 | T18: 0 | W18: - Long Term Debt | X18: 7019863 | Y18: 7019863 | Z18: 7019863 | AA18: 7019863 | AB18: 7019863 | AC18: 7019863
B19: Depreciation (2020-25) | C19: 420072 , 402711 , 326661 , 311583 , 262919 , 125551 | F19: EBIT | G19: =G17-G18 -> -385872 | H19: =H17-H18 -> -128256 | I19: =I17-I18 -> 345753.75 | J19: =J17-J18 -> 547570.93 | K19: =K17-K18 -> 694937.73 | L19: =L17-L18 -> 841884.3 | N19: Net Increase in Cash | O19: =O13+O15+SUM(O17:O18) -> -999578.5 | P19: =P13+P15+SUM(P17:P18) -> 165021.61 | Q19: =Q13+Q15+SUM(Q17:Q18) -> 565414.86 | R19: =R13+R15+SUM(R17:R18) -> 755274.05 | S19: =S13+S15+SUM(S17:S18) -> 855599.25 | T19: =T13+T15+SUM(T17:T18) -> 866005.24 | W19: Total Liabilities | X19: =X17+X18 -> 8101978 | Y19: =Y17+Y18 -> 8168172.1 | Z19: =Z17+Z18 -> 8209889.3 | AA19: =AA17+AA18 -> 8255690.3 | AB19: =AB17+AB18 -> 8279506.9 | AC19: =AC17+AC18 -> 8291653.3 | AD19: since new loan is short term we didn't change the long term loand amount what we got 2019e from exibhit 6.
B20: Interest Expense Rate | C20: 170k per year for pervious debt + if any other finance option taken | F20: Interest | G20: 170000 | H20: 170000 | I20: 170000 | J20: 170000 | K20: 170000 | L20: 170000 | N20: Net cash flow | O20: 991610 | P20: =O21 -> -7968.5 | Q20: =P21 -> 157053.11 | R20: =Q21 -> 722467.97 | S20: =R21 -> 1477742 | T20: =S21 -> 2333341.3 | W20: Equity
B21: State Tax | C21: 0% for federal due to loss carryforwards; $15,000 minimum Oregon state tax each year | F21: Income before tax | G21: =G19-G20 -> -555872 | H21: =H19-H20 -> -298256 | I21: =I19-I20 -> 175753.75 | J21: =J19-J20 -> 377570.93 | K21: =K19-K20 -> 524937.73 | L21: =L19-L20 -> 671884.3 | N21: Closing Cash Balance | O21: =O19+O20 -> -7968.5 | P21: =P19+P20 -> 157053.11 | Q21: =Q19+Q20 -> 722467.97 | R21: =R19+R20 -> 1477742 | S21: =S19+S20 -> 2333341.3 | T21: =T19+T20 -> 3199346.5 | W21: - Shareholder's Equity | X21: =9173230+5000000 -> 14173230 | Y21: =9173230+5000000 -> 14173230 | Z21: =9173230+5000000 -> 14173230 | AA21: =9173230+5000000 -> 14173230 | AB21: =9173230+5000000 -> 14173230 | AC21: =9173230+5000000 -> 14173230
B22: Forecast year | C22: 2020–2025 | F22: Fixed State Tax | G22: 15000 | H22: =Table5[[#This Row],[2020]] -> 15000 | I22: =Table5[[#This Row],[2021]] -> 15000 | J22: =Table5[[#This Row],[2022]] -> 15000 | K22: =Table5[[#This Row],[2023]] -> 15000 | L22: =Table5[[#This Row],[2024]] -> 15000 | W22: - Retained Earnings | X22: =' Green Zebra Historic Data'!E38 + G23 -> -11167562 | Y22: =Table3[[#This Row],[2020]]+H23 -> -11480818 | Z22: =Table3[[#This Row],[2021]]+I23 -> -11320064 | AA22: =Table3[[#This Row],[2022]]+J23 -> -10957493 | AB22: =Table3[[#This Row],[2023]]+K23 -> -10447556 | AC22: =Table3[[#This Row],[2024]]+L23 -> -9790671.3 | AD22: (5million debt converted to Equity)
F23: Net Income | G23: =G21-G22 -> -570872 | H23: =H21-H22 -> -313256 | I23: =I21-I22 -> 160753.75 | J23: =J21-J22 -> 362570.93 | K23: =K21-K22 -> 509937.73 | L23: =L21-L22 -> 656884.3 | N23: amra cashflow statement korsi but green zebra oikhane bola ase cash hole sells eer 2%. tahole amra konta nibo? | W23: - Current Year Earnings | X23: =G23 -> -570872 | Y23: =H23 -> -313256 | Z23: =I23 -> 160753.75 | AA23: =J23 -> 362570.93 | AB23: =K23 -> 509937.73 | AC23: =L23 -> 656884.3
W24: Total Net Equity | X24: =SUM(X21:X23) -> 2434796 | Y24: =SUM(Y21:Y23) -> 2379156 | Z24: =SUM(Z21:Z23) -> 3013919.5 | AA24: =SUM(AA21:AA23) -> 3578307.6 | AB24: =SUM(AB21:AB23) -> 4235612.1 | AC24: =SUM(AC21:AC23) -> 5039443
W25: Total Liab & Equity | X25: =X24+X19 -> 10536774 | Y25: 7063969 | Z25: 8063665 | AA25: 9815277 | AB25: 10400839 | AC25: 10286601
C26: What will be the tax rate if company become profitable ? | F26: Income Statement FC20-25 if 2.2m bridge loan taken | N26: Cash Flow Statement: if bridge loan taken | W26: EFN | X26: =X25-X12 -> 6306080.5 | Y26: =Y25-Y12 -> 3168488.5 | Z26: =Z25-Z12 -> 4468310.2 | AA26: =AA25-AA12 -> 6477714.5 | AB26: =AB25-AB12 -> 7262464.3 | AC26: =AC25-AC12 -> 7240845
F28: Name | G28: 2020 | H28: 2021 | I28: 2022 | J28: 2023 | K28: 2024 | L28: 2025 | N28: Item | O28: 2020 | P28: 2021 | Q28: 2022 | R28: 2023 | S28: 2024 | T28: 2025 | W28: Balance Sheet: | AD28: *No inforamtion was found for accout receiveable
F29: Sales | G29: =G7 -> 17100000 | H29: =H7 -> 18297000 | I29: =I7 -> 19211850 | J29: =J7 -> 19980324 | K29: =K7 -> 20379930 | L29: =L7 -> 20583730 | N29: Net Income | O29: =G23 -> -570872 | P29: =H23 -> -313256 | Q29: =I23 -> 160753.75 | R29: =J23 -> 362570.93 | S29: =K23 -> 509937.73 | T29: =L23 -> 656884.3 | W29: Item | X29: 2020 | Y29: 2021 | Z29: 2022 | AA29: 2023 | AB29: 2024 | AC29: 2025
B30: =2.2*1000000 -> 2200000 | C30: =(B30*12.5%) -> 275000 | D30: =(B30*6.25%) -> 137500 | F30: Growth (%) | H30: =H8 -> 0.07 | I30: =I8 -> 0.05 | J30: =J8 -> 0.04 | K30: =K8 -> 0.02 | L30: =L8 -> 0.01 | N30: Adjustments for: | W30: Assets
F31: COGS (% of Sales) | G31: 0.595 | H31: 0.59 | I31: 0.58 | J31: 0.58 | K31: 0.58 | L31: 0.58 | N31: +Depreciation | O31: =G18 -> 420072 | P31: =H18 -> 402711 | Q31: =I18 -> 326661 | R31: =J18 -> 311583 | S31: =K18 -> 262919 | T31: =L18 -> 125551 | W31: Cash & Equivalents | X31: =X7 -> 342000 | Y31: =Y7 -> 365940 | Z31: =Z7 -> 384237 | AA31: =AA7 -> 399606.48 | AB31: =AB7 -> 407598.61 | AC31: =AC7 -> 411674.6
F32: COGS | G32: =G29*G31 -> 10174500 | H32: =H29*H31 -> 10795230 | I32: =I29*I31 -> 11142873 | J32: =J29*J31 -> 11588588 | K32: =K29*K31 -> 11820360 | L32: =L29*L31 -> 11938563 | N32: Changes in Working Capital: | W32: Inventory | X32: =X8 -> 640993.5 | Y32: =Y8 -> 680099.49 | Z32: =Z8 -> 702001 | AA32: =AA8 -> 730081.04 | AB32: =AB8 -> 744682.66 | AC32: =AC8 -> 752129.49
F33: Gross Profit | G33: =G29-(G29*G31) -> 6925500 | H33: =H29-(H29*H31) -> 7501770 | I33: =I29-(I29*I31) -> 8068977 | J33: =J29-(J29*J31) -> 8391736.1 | K33: =K29-(K29*K31) -> 8559570.8 | L33: =L29-(L29*L31) -> 8645166.5 | N33: - Inventories | O33: =O11 -> 640993.5 | P33: =P11 -> 680099.49 | Q33: =Q11 -> 702001 | R33: =R11 -> 730081.04 | S33: =S11 -> 744682.66 | T33: =T11 -> 752129.49 | U33: Exihibit 7 - 6.3% of cogs | W33: Other Current Assets | X33: 25000 | Y33: 25000 | Z33: 25000 | AA33: 25000 | AB33: 25000 | AC33: 25000
B34: for balance sheet | F34: Payroll & Benefits (%) | G34: 0.253 | H34: 0.25 | I34: 0.245 | J34: 0.242 | K34: 0.24 | L34: 0.24 | N34: + Accounts Payable | O34: =O12 -> 712215 | P34: =P12 -> 755666.1 | Q34: =Q12 -> 780001.11 | R34: =R12 -> 811201.15 | S34: =S12 -> 827425.18 | T34: =T12 -> 835699.43 | U34: Exihibit 7 - 7% of cogs | W34: Total Current Assets | X34: =SUM(X31:X33) -> 1007993.5 | Y34: =SUM(Y31:Y33) -> 1071039.5 | Z34: =SUM(Z31:Z33) -> 1111238 | AA34: =SUM(AA31:AA33) -> 1154687.5 | AB34: =SUM(AB31:AB33) -> 1177281.3 | AC34: =SUM(AC31:AC33) -> 1188804.1
B35: cash | C35: 2% of Sales | F35: Payroll & Benefits | G35: =G29*G34 -> 4326300 | H35: =H29*H34 -> 4574250 | I35: =I29*I34 -> 4706903.2 | J35: =J29*J34 -> 4835238.4 | K35: =K29*K34 -> 4891183.3 | L35: =L29*L34 -> 4940095.1 | N35: Cash from Operations | O35: =O29+O31-O33+O34 -> -79578.5 | P35: =P29+P31-P33+P34 -> 165021.61 | Q35: =Q29+Q31-Q33+Q34 -> 565414.86 | R35: =R29+R31-R33+R34 -> 755274.05 | S35: =S29+S31-S33+S34 -> 855599.25 | T35: =T29+T31-T33+T34 -> 866005.24 | W35: Fixed Assets (net) | X35: =G7*S2 -> 3197700 | Y35: =H7*T2 -> 2799441 | Z35: =I7*U2 -> 2459116.8 | AA35: =J7*V2 -> 2157875 | AB35: =K7*W2 -> 1936093.4 | AC35: =L7*X2 -> 1831952
B36: Inventories | C36: 6.3% of COGS | F36: Occupancy & Other (%) | G36: 0.14 | H36: 0.135 | I36: 0.13 | J36: 0.125 | K36: 0.123 | L36: 0.123 | N36: Cash from Investing: | W36: Total Assets | X36: =X34+X35 -> 4205693.5 | Y36: =Y34+Y35 -> 3870480.5 | Z36: =Z34+Z35 -> 3570354.8 | AA36: =AA34+AA35 -> 3312562.5 | AB36: =AB34+AB35 -> 3113374.7 | AC36: =AC34+AC35 -> 3020756
B37: Accounts Payable | C37: 7.0% of COGS | F37: Occupancy & Other | G37: =G29*G36 -> 2394000 | H37: =H29*H36 -> 2470095 | I37: =I29*I36 -> 2497540.5 | J37: =J29*J36 -> 2497540.5 | K37: =K29*K36 -> 2506731.4 | L37: =L29*L36 -> 2531798.8 | N37: - Capital Expenditures | O37: =C7 -> 920000 | P37: 0 | Q37: 0 | R37: 0 | S37: 0 | T37: 0 | W37: Liabilities
B38: Current Liabilities | C38: 1.9% of Sales | F38: Advertising (1% of Sales) | G38: =1%*G29 -> 171000 | H38: =1%*H29 -> 182970 | I38: =1%*I29 -> 192118.5 | J38: =1%*J29 -> 199803.24 | K38: =1%*K29 -> 203799.3 | L38: =1%*L29 -> 205837.3 | N38: Cash from Financing: | W38: Accounts Payable | X38: =X14 -> 712215 | Y38: =Y14 -> 755666.1 | Z38: =Z14 -> 780001.11 | AA38: =AA14 -> 811201.15 | AB38: =AB14 -> 827425.18 | AC38: =AC14 -> 835699.43
F39: EBITDA | G39: =G33-(G35+G37+G38) -> 34200 | H39: =H33-(H35+H37+H38) -> 274455 | I39: =I33-(I35+I37+I38) -> 672414.75 | J39: =J33-(J35+J37+J38) -> 859153.93 | K39: =K33-(K35+K37+K38) -> 957856.73 | L39: =L33-(L35+L37+L38) -> 967435.3 | N39: Loan Received | O39: =2200000-180000 -> 2020000 | P39: 0 | Q39: 0 | R39: 0 | S39: 0 | T39: 0 | W39: Other Current Liabilities | X39: =X15 -> 324900 | Y39: =Y15 -> 347643 | Z39: =Z15 -> 365025.15 | AA39: =AA15 -> 379626.16 | AB39: =AB15 -> 387218.68 | AC39: =AC15 -> 391090.87
F40: Depreciation | G40: 420072 | H40: 402711 | I40: 326661 | J40: 311583 | K40: 262919 | L40: 125551 | N40: - Loan Repayment | O40: 0 | P40: -2200000 | Q40: 0 | R40: 0 | S40: 0 | T40: 0 | W40: Line of Credit | X40: 45000 | Y40: 45000 | Z40: 45000 | AA40: 45000 | AB40: 45000 | AC40: 45000
F41: EBIT | G41: =G39-G40 -> -385872 | H41: =H39-H40 -> -128256 | I41: =I39-I40 -> 345753.75 | J41: =J39-J40 -> 547570.93 | K41: =K39-K40 -> 694937.73 | L41: =L39-L40 -> 841884.3 | N41: - Interest Paid | O41: =-G42 -> -625000 | P41: =-H42+138000 -> -169500 | Q41: =-I42 -> -170000 | R41: =-J42 -> -170000 | S41: =-K42 -> -170000 | T41: =-L42 -> -170000 | W41: Short-Term Loan (New) | X41: 2200000 | Y41: 0 | Z41: 0 | AA41: 0 | AB41: 0 | AC41: 0
F42: Interest | G42: =G20+$C$30+180000 -> 625000 | H42: =H20+$D$30 -> 307500 | I42: =I20 -> 170000 | J42: =K20 -> 170000 | K42: =K20 -> 170000 | L42: =L20 -> 170000 | M42: 180000 have to pay when taking loan | N42: Net Increase in Cash | O42: =O35-O37+SUM(O39:O41) -> 395421.5 | P42: =P35-P37+SUM(P39:P41) -> -2204478.4 | Q42: =Q35-Q37+SUM(Q39:Q41) -> 395414.86 | R42: =R35-R37+SUM(R39:R41) -> 585274.05 | S42: =S35-S37+SUM(S39:S41) -> 685599.25 | T42: =T35-T37+SUM(T39:T41) -> 696005.24 | W42: Total Current Liabilities | X42: =SUM(X38:X41) -> 3282115 | Y42: =SUM(Y38:Y41) -> 1148309.1 | Z42: =SUM(Z38:Z41) -> 1190026.3 | AA42: =SUM(AA38:AA41) -> 1235827.3 | AB42: =SUM(AB38:AB41) -> 1259643.9 | AC42: =SUM(AC38:AC41) -> 1271790.3
F43: Income before tax | G43: =G41-G42 -> -1010872 | H43: =H41-H42 -> -435756 | I43: =I41-I42 -> 175753.75 | J43: =J41-J42 -> 377570.93 | K43: =K41-K42 -> 524937.73 | L43: =L41-L42 -> 671884.3 | N43: Opening Cash Balance | O43: 991610 | P43: =O44 -> 1387031.5 | Q43: =P44 -> -817446.89 | R43: =Q44 -> -422032.03 | S43: =R44 -> 163242.02 | T43: =S44 -> 848841.27 | W43: Long Term Debt | X43: =7019863-5000000 -> 2019863 | Y43: =7019863-5000000 -> 2019863 | Z43: =7019863-5000000 -> 2019863 | AA43: =7019863-5000000 -> 2019863 | AB43: =7019863-5000000 -> 2019863 | AC43: =7019863-5000000 -> 2019863
F44: Fixed State Tax | G44: 15000 | H44: 15000 | I44: =Table6[[#This Row],[2020]] -> 15000 | J44: =Table6[[#This Row],[2021]] -> 15000 | K44: =Table6[[#This Row],[2022]] -> 15000 | L44: =Table6[[#This Row],[2023]] -> 15000 | N44: Closing Cash Balance | O44: =O42+O43 -> 1387031.5 | P44: =P42+P43 -> -817446.89 | Q44: =Q42+Q43 -> -422032.03 | R44: =R42+R43 -> 163242.02 | S44: =S42+S43 -> 848841.27 | T44: =T42+T43 -> 1544846.5 | W44: Total Liabilities | X44: =SUM(X42:X43) -> 5301978 | Y44: =SUM(Y42:Y43) -> 3168172.1 | Z44: =SUM(Z42:Z43) -> 3209889.3 | AA44: =SUM(AA42:AA43) -> 3255690.3 | AB44: =SUM(AB42:AB43) -> 3279506.9 | AC44: =SUM(AC42:AC43) -> 3291653.3
F45: Net Income | G45: =G43-G44 -> -1025872 | H45: =H43-H44 -> -450756 | I45: =I43-I44 -> 160753.75 | J45: =J43-J44 -> 362570.93 | K45: =K43-K44 -> 509937.73 | L45: =L43-L44 -> 656884.3 | W45: Equity
W46: Shareholder's Equity | X46: =9173230+5000000 -> 14173230 | Y46: =9173230+5000000 -> 14173230 | Z46: =9173230+5000000 -> 14173230 | AA46: =9173230+5000000 -> 14173230 | AB46: =9173230+5000000 -> 14173230 | AC46: =9173230+5000000 -> 14173230
W47: Retained Earnings | X47: =' Green Zebra Historic Data'!E38 + '1-Store Portland Expansion'!G45 -> -11622562 | Y47: =X47 + '1-Store Portland Expansion'!H45 -> -12073318 | Z47: =Y47 + '1-Store Portland Expansion'!I45 -> -11912564 | AA47: =Z47 + '1-Store Portland Expansion'!J45 -> -11549993 | AB47: =AA47 + '1-Store Portland Expansion'!K45 -> -11040056 | AC47: =AB47 + '1-Store Portland Expansion'!L45 -> -10383171
W48: Current Year Earnings | X48: =G45 -> -1025872 | Y48: =H45 -> -450756 | Z48: =I45 -> 160753.75 | AA48: =J45 -> 362570.93 | AB48: =K45 -> 509937.73 | AC48: =L45 -> 656884.3
W49: Total Net Equity | X49: =X46+X47+X48 -> 1524796 | Y49: =Y46+Y47+Y48 -> 1649156 | Z49: =Z46+Z47+Z48 -> 2421419.5 | AA49: =AA46+AA47+AA48 -> 2985807.6 | AB49: =AB46+AB47+AB48 -> 3643112.1 | AC49: =AC46+AC47+AC48 -> 4446943
W50: Total Liab & Equity | X50: =X44+X49 -> 6826774 | Y50: =Y44+Y49 -> 4817328.1 | Z50: =Z44+Z49 -> 5631308.8 | AA50: =AA44+AA49 -> 6241497.9 | AB50: =AB44+AB49 -> 6922619 | AC50: =AC44+AC49 -> 7738596.3
W51: EFN | X51: =X50-X36 -> 2621080.5 | Y51: =Y50-Y36 -> 946847.61 | Z51: =Z50-Z36 -> 2060954 | AA51: =AA50-AA36 -> 2928935.4 | AB51: =AB50-AB36 -> 3809244.3 | AC51: =AC50-AC36 -> 4717840.3
F53: Income Statement FC20-25 if 2.2m mixed loan taken | N53: Cash Flow Statement: vc
F55: Name | G55: 2020 | H55: 2021 | I55: 2022 | J55: 2023 | K55: 2024 | L55: 2025 | N55: Item | O55: 2020 | P55: 2021 | Q55: 2022 | R55: 2023 | S55: 2024 | T55: 2025 | W55: Item | X55: 2020 | Y55: 2021 | Z55: 2022 | AA55: 2023 | AB55: 2024 | AC55: 2025
F56: Sales | G56: =G29 -> 17100000 | H56: =H29 -> 18297000 | I56: =I29 -> 19211850 | J56: =J29 -> 19980324 | K56: =K29 -> 20379930 | L56: =L29 -> 20583730 | N56: Net Income | O56: =G72 -> -685872 | P56: =H72 -> -428256 | Q56: =I72 -> 45753.75 | R56: =J72 -> 247570.93 | S56: =K72 -> 394937.73 | T56: =L72 -> 541884.3 | W56: Assets
F57: Growth (%) | G57: – | H57: =H30 -> 0.07 | I57: =I30 -> 0.05 | J57: =J30 -> 0.04 | K57: =K30 -> 0.02 | L57: =L30 -> 0.01 | N57: Adjustments for: | W57: Cash & Equivalents | X57: =X31 -> 342000 | Y57: =Y31 -> 365940 | Z57: =Z31 -> 384237 | AA57: =AA31 -> 399606.48 | AB57: =AB31 -> 407598.61 | AC57: =AC31 -> 411674.6
F58: COGS (% of Sales) | G58: 0.595 | H58: 0.59 | I58: 0.58 | J58: 0.58 | K58: 0.58 | L58: 0.58 | N58: +Depreciation | O58: =G67 -> 420072 | P58: =H67 -> 402711 | Q58: =I67 -> 326661 | R58: =J67 -> 311583 | S58: =K67 -> 262919 | T58: =L67 -> 125551 | W58: Inventory | X58: =X32 -> 640993.5 | Y58: =Y32 -> 680099.49 | Z58: =Z32 -> 702001 | AA58: =AA32 -> 730081.04 | AB58: =AB32 -> 744682.66 | AC58: =AC32 -> 752129.49
F59: COGS | G59: =G56*G58 -> 10174500 | H59: =H56*H58 -> 10795230 | I59: =I56*I58 -> 11142873 | J59: =J56*J58 -> 11588588 | K59: =K56*K58 -> 11820360 | L59: =L56*L58 -> 11938563 | N59: Changes in Working Capital: | W59: Other Current Assets | X59: =X33 -> 25000 | Y59: =Y33 -> 25000 | Z59: =Z33 -> 25000 | AA59: =AA33 -> 25000 | AB59: =AB33 -> 25000 | AC59: =AC33 -> 25000
F60: Gross Profit | G60: =G56-(G56*G58) -> 6925500 | H60: =H56-(H56*H58) -> 7501770 | I60: =I56-(I56*I58) -> 8068977 | J60: =J56-(J56*J58) -> 8391736.1 | K60: =K56-(K56*K58) -> 8559570.8 | L60: =L56-(L56*L58) -> 8645166.5 | N60: - Inventories | O60: =O11 -> 640993.5 | P60: =P11 -> 680099.49 | Q60: =Q11 -> 702001 | R60: =R11 -> 730081.04 | S60: =S11 -> 744682.66 | T60: =T11 -> 752129.49 | W60: Total Current Assets | X60: =SUM(X57:X59) -> 1007993.5 | Y60: =SUM(Y57:Y59) -> 1071039.5 | Z60: =SUM(Z57:Z59) -> 1111238 | AA60: =SUM(AA57:AA59) -> 1154687.5 | AB60: =SUM(AB57:AB59) -> 1177281.3 | AC60: =SUM(AC57:AC59) -> 1188804.1
F61: Payroll & Benefits (%) | G61: 0.253 | H61: 0.25 | I61: 0.245 | J61: 0.242 | K61: 0.24 | L61: 0.24 | N61: + Accounts Payable | O61: =O12 -> 712215 | P61: =P12 -> 755666.1 | Q61: =Q12 -> 780001.11 | R61: =R12 -> 811201.15 | S61: =S12 -> 827425.18 | T61: =T12 -> 835699.43 | W61: Fixed Assets (net) | X61: =X35 -> 3197700 | Y61: =Y35 -> 2799441 | Z61: =Z35 -> 2459116.8 | AA61: =AA35 -> 2157875 | AB61: =AB35 -> 1936093.4 | AC61: =AC35 -> 1831952
F62: Payroll & Benefits | G62: =G56*G61 -> 4326300 | H62: =H56*H61 -> 4574250 | I62: =I56*I61 -> 4706903.2 | J62: =J56*J61 -> 4835238.4 | K62: =K56*K61 -> 4891183.3 | L62: =L56*L61 -> 4940095.1 | N62: Cash from Operations | O62: =O56+O58-O60+O61 -> -194578.5 | P62: =P56+P58-P60+P61 -> 50021.61 | Q62: =Q56+Q58-Q60+Q61 -> 450414.86 | R62: =R56+R58-R60+R61 -> 640274.05 | S62: =S56+S58-S60+S61 -> 740599.25 | T62: =T56+T58-T60+T61 -> 751005.24 | W62: Total Assets | X62: =X60+X61 -> 4205693.5 | Y62: =Y60+Y61 -> 3870480.5 | Z62: =Z60+Z61 -> 3570354.8 | AA62: =AA60+AA61 -> 3312562.5 | AB62: =AB60+AB61 -> 3113374.7 | AC62: =AC60+AC61 -> 3020756
F63: Occupancy & Other (%) | G63: 0.14 | H63: 0.135 | I63: 0.13 | J63: 0.125 | K63: 0.123 | L63: 0.123 | N63: Cash from Investing: | W63: Liabilities
F64: Occupancy & Other | G64: =G56*G63 -> 2394000 | H64: =H56*H63 -> 2470095 | I64: =I56*I63 -> 2497540.5 | J64: =J56*J63 -> 2497540.5 | K64: =K56*K63 -> 2506731.4 | L64: =L56*L63 -> 2531798.8 | N64: - Capital Expenditures | O64: =O37 -> 920000 | P64: =P37 -> 0 | Q64: =Q37 -> 0 | R64: =R37 -> 0 | S64: =S37 -> 0 | T64: =T37 -> 0 | W64: Accounts Payable | X64: =X38 -> 712215 | Y64: =Y38 -> 755666.1 | Z64: =Z38 -> 780001.11 | AA64: =AA38 -> 811201.15 | AB64: =AB38 -> 827425.18 | AC64: =AC38 -> 835699.43
F65: Advertising (1% of Sales) | G65: =1%*G56 -> 171000 | H65: =1%*H56 -> 182970 | I65: =1%*I56 -> 192118.5 | J65: =1%*J56 -> 199803.24 | K65: =1%*K56 -> 203799.3 | L65: =1%*L56 -> 205837.3 | N65: Cash from Financing: | W65: Other Current Liabilities | X65: =X39 -> 324900 | Y65: =Y39 -> 347643 | Z65: =Z39 -> 365025.15 | AA65: =AA39 -> 379626.16 | AB65: =AB39 -> 387218.68 | AC65: =AC39 -> 391090.87
F66: EBITDA | G66: =G60-(G62+G64+G65) -> 34200 | H66: =H60-(H62+H64+H65) -> 274455 | I66: =I60-(I62+I64+I65) -> 672414.75 | J66: =J60-(J62+J64+J65) -> 859153.93 | K66: =K60-(K62+K64+K65) -> 957856.73 | L66: =L60-(L62+L64+L65) -> 967435.3 | N66: - VC Investment | O66: 12000000 | P66: 0 | Q66: 0 | R66: 0 | S66: 0 | T66: 0 | W66: Line of Credit | X66: 45000 | Y66: 45000 | Z66: 45000 | AA66: 45000 | AB66: 45000 | AC66: 45000
F67: Depreciation | G67: 420072 | H67: 402711 | I67: 326661 | J67: 311583 | K67: 262919 | L67: 125551 | N67: - Loan Repayment | O67: 0 | P67: 0 | Q67: 0 | R67: 0 | S67: 0 | T67: 0 | W67: Short-Term Loan (New) | X67: 2200000 | Y67: 0 | Z67: 0 | AA67: 0 | AB67: 0 | AC67: 0
F68: EBIT | G68: =G66-G67 -> -385872 | H68: =H66-H67 -> -128256 | I68: =I66-I67 -> 345753.75 | J68: =J66-J67 -> 547570.93 | K68: =K66-K67 -> 694937.73 | L68: =L66-L67 -> 841884.3 | N68: - Interest Paid | O68: =-G69 -> -285000 | P68: =-H69 -> -285000 | Q68: =-I69 -> -285000 | R68: =-J69 -> -285000 | S68: =-K69 -> -285000 | T68: =-L69 -> -285000 | W68: Total Current Liabilities | X68: =SUM(X64:X67) -> 3282115 | Y68: =SUM(Y64:Y67) -> 1148309.1 | Z68: =SUM(Z64:Z67) -> 1190026.3 | AA68: =SUM(AA64:AA67) -> 1235827.3 | AB68: =SUM(AB64:AB67) -> 1259643.9 | AC68: =SUM(AC64:AC67) -> 1271790.3
F69: Interest | G69: =G20+115000 -> 285000 | H69: =H20+115000 -> 285000 | I69: =I20+115000 -> 285000 | J69: =J20+115000 -> 285000 | K69: =K20+115000 -> 285000 | L69: =L20+115000 -> 285000 | N69: Net Increase in Cash | O69: =O62-O64+SUM(O66:O68) -> 10600422 | P69: =P62-P64+SUM(P66:P68) -> -234978.39 | Q69: =Q62-Q64+SUM(Q66:Q68) -> 165414.86 | R69: =R62-R64+SUM(R66:R68) -> 355274.05 | S69: =S62-S64+SUM(S66:S68) -> 455599.25 | T69: =T62-T64+SUM(T66:T68) -> 466005.24 | W69: Long Term Debt | X69: =X43 -> 2019863 | Y69: =Y43 -> 2019863 | Z69: =Z43 -> 2019863 | AA69: =AA43 -> 2019863 | AB69: =AB43 -> 2019863 | AC69: =AC43 -> 2019863
F70: Income before tax | G70: =G68-G69 -> -670872 | H70: =H68-H69 -> -413256 | I70: =I68-I69 -> 60753.75 | J70: =J68-J69 -> 262570.93 | K70: =K68-K69 -> 409937.73 | L70: =L68-L69 -> 556884.3 | N70: Opening Cash Balance | O70: 991610 | P70: =O71 -> 11592032 | Q70: =P71 -> 11357053 | R70: =Q71 -> 11522468 | S70: =R71 -> 11877742 | T70: =S71 -> 12333341 | W70: Total Liabilities | X70: =SUM(X68:X69) -> 5301978 | Y70: =SUM(Y68:Y69) -> 3168172.1 | Z70: =SUM(Z68:Z69) -> 3209889.3 | AA70: =SUM(AA68:AA69) -> 3255690.3 | AB70: =SUM(AB68:AB69) -> 3279506.9 | AC70: =SUM(AC68:AC69) -> 3291653.3
F71: Fixed State Tax | G71: 15000 | H71: =Table7[[#This Row],[2020]] -> 15000 | I71: =Table7[[#This Row],[2021]] -> 15000 | J71: =Table7[[#This Row],[2022]] -> 15000 | K71: =Table7[[#This Row],[2023]] -> 15000 | L71: =Table7[[#This Row],[2024]] -> 15000 | N71: Closing Cash Balance | O71: =O69+O70 -> 11592032 | P71: =P69+P70 -> 11357053 | Q71: =Q69+Q70 -> 11522468 | R71: =R69+R70 -> 11877742 | S71: =S69+S70 -> 12333341 | T71: =T69+T70 -> 12799347 | W71: Equity
F72: Net Income | G72: =G70-G71 -> -685872 | H72: =H70-H71 -> -428256 | I72: =I70-I71 -> 45753.75 | J72: =J70-J71 -> 247570.93 | K72: =K70-K71 -> 394937.73 | L72: =L70-L71 -> 541884.3 | W72: Shareholder's Equity | X72: =9173230+5000000 -> 14173230 | Y72: =9173230+5000000 -> 14173230 | Z72: =9173230+5000000 -> 14173230 | AA72: =9173230+5000000 -> 14173230 | AB72: =9173230+5000000 -> 14173230 | AC72: =9173230+5000000 -> 14173230
W73: Retained Earnings | X73: =X47 -> -11622562 | Y73: =X73 + H72 -> -12050818 | Z73: =Y73 + '1-Store Portland Expansion'!I71 -> -12035818 | AA73: =Z73 + '1-Store Portland Expansion'!J71 -> -12020818 | AB73: =AA73 + '1-Store Portland Expansion'!K71 -> -12005818 | AC73: =AB73 + '1-Store Portland Expansion'!L71 -> -11990818
W74: Current Year Earnings | X74: =G72 -> -685872 | Y74: =H72 -> -428256 | Z74: =I72 -> 45753.75 | AA74: =J72 -> 247570.93 | AB74: =K72 -> 394937.73 | AC74: =L72 -> 541884.3
W75: Total Net Equity | X75: =X72+X73+X74 -> 1864796 | Y75: =Y72+Y73+Y74 -> 1694156 | Z75: =Z72+Z73+Z74 -> 2183165.8 | AA75: =AA72+AA73+AA74 -> 2399982.9 | AB75: =AB72+AB73+AB74 -> 2562349.7 | AC75: =AC72+AC73+AC74 -> 2724296.3
W76: Total Liab & Equity | X76: =X70+X75 -> 7166774 | Y76: =Y70+Y75 -> 4862328.1 | Z76: =Z70+Z75 -> 5393055 | AA76: =AA70+AA75 -> 5655673.2 | AB76: =AB70+AB75 -> 5841856.6 | AC76: =AC70+AC75 -> 6015949.6
W77: EFN | X77: =X76-X62 -> 2961080.5 | Y77: =Y76-Y62 -> 991847.61 | Z77: =Z76-Z62 -> 1822700.2 | AA77: =AA76-AA62 -> 2343110.7 | AB77: =AB76-AB62 -> 2728481.9 | AC77: =AC76-AC62 -> 2995193.6

Sheet GZ Competitors AND WACC
F1: This 3 can consider as competitor as GZ consider themself as C-store | M1: {=F2:H3} -> CASY | N1: ANCUF | O1: ANCADRNY
A2: Column1 | B2: CMG | C2: SFM | D2: VLGEA | E2: KR | F2: CASY | G2: ANCUF | H2: ANCADRNY | I2: WMT | M2: C-Store | N2: C-Store | O2: C-Store
A3: Positioning | B3: Fast Casual | C3: Natural & Organie | D3: Grocery | E3: Grocery | F3: C-Store | G3: C-Store | H3: C-Store | I3: Supercenters and Wholesalers | L3: =A5 -> TTM Revenues ($ Bil) | M3: =F5*1000000000 -> 9400000000 | N3: =G5*1000000000 -> 58500000000 | O3: =H5*1000000000 -> 64500000000
L4: =A6 -> EBITDA ($ Mil) | M4: =F6*1000000000 -> 586900000000 | N4: =G6*1000000000 -> 3700000000000 | O4: =H6*1000000000 -> 4300000000000
A5: TTM Revenues ($ Bil) | B5: 5.2 | C5: 5.4 | D5: 1.6 | E5: 120.9 | F5: 9.4 | G5: 58.5 | H5: 64.5 | I5: 518 | L5: =A23 -> Ent. Value to EBITDA | M5: =F23*1000000000 -> 12500000000 | N5: =G23*1000000000 -> 11700000000 | O5: =H23*1000000000 -> 5900000000
A6: EBITDA ($ Mil) | B6: 644.4 | C6: 369.5 | D6: 67.3 | E6: 5700 | F6: 586.9 | G6: 3700 | H6: 4300 | I6: 31.7 | K6: Industry EV/Revenue | L6: =M5/M3 -> 1.3297872 | M6: =N5/N3 -> 0.2 | N6: =O5/O3 -> 0.091472868 | O6: Avg | P6: =AVERAGE(L6:N6) -> 0.54042003
A7: 3yr Revenue growth rate % | B7: 0.026 | C7: 0.132 | D7: 0.006 | E7: 0.033 | F7: 0.095 | G7: 0.201 | H7: 0.18 | I7: 0.022 | K7: Industry EV/EBITDA | L7: =M5/M4 -> 0.021298347 | M7: =N5/N4 -> 0.0031621622 | N7: =O5/O4 -> 0.001372093 | O7: Avg | P7: =AVERAGE(L7:N7) -> 0.0086108675
A8: ROE % | B8: 0.17 | C8: 0.251 | D8: 0.079 | E8: 0.234 | F8: 0.157 | G8: 0.222 | H8: 0.124 | I8: 0.182
A9: ROIC % | B9: 0.06 | C9: 0.094 | D9: 0.067 | E9: 0.09 | F9: 0.08 | G9: 0.123 | H9: 0.108 | I9: 0.108
A10: EBITDA Margin % | B10: 0.124 | C10: 0.068 | D10: 0.041 | E10: 0.047 | F10: 0.063 | G10: 0.063 | H10: 0.067 | I10: 0.061
A11: Net Margin | B11: 0.048 | C11: 0.026 | D11: 0.015 | E11: 0.015 | F11: 0.023 | G11: 0.033 | H11: 0.027 | I11: 0.025 | K11: If 1-Store expasion in Portland | L11: 2020 | M11: 2021 | N11: 2022 | O11: 2023 | P11: 2024 | Q11: 2025
A13: Market Capitalization ($ Bil) | B13: 23.4 | C13: 2.3 | D13: 0.3727 | E13: 20.6 | F13: 6.2 | G13: 35.2 | H13: 27.2 | I13: 334.5 | K13: Projected Revenue | L13: ='1-Store Portland Expansion'!G7 -> 17100000 | M13: ='1-Store Portland Expansion'!H7 -> 18297000 | N13: ='1-Store Portland Expansion'!I7 -> 19211850 | O13: ='1-Store Portland Expansion'!J7 -> 19980324 | P13: ='1-Store Portland Expansion'!K7 -> 20379930 | Q13: ='1-Store Portland Expansion'!L7 -> 20583730
A14: Enterprise Value ($ Bil) | B14: 14.5 | C14: 3.9 | D14: 0.3169 | E14: 40.5 | F14: 7.3 | G14: 43.5 | H14: 28.4 | I14: 398.2 | K14: EV | L14: =L13*$P$6 -> 9241182.6 | M14: =M13*$P$6 -> 9888065.4 | N14: =N13*$P$6 -> 10382469 | O14: =O13*$P$6 -> 10797767 | P14: =P13*$P$6 -> 11013723 | Q14: =Q13*$P$6 -> 11123860
A15: Book Value | K15: Net Debt | L15: ='1-Store Portland Expansion'!X19 -> 8101978 | M15: ='1-Store Portland Expansion'!Y19 -> 8168172.1 | N15: ='1-Store Portland Expansion'!Z19 -> 8209889.3 | O15: ='1-Store Portland Expansion'!AA19 -> 8255690.3 | P15: ='1-Store Portland Expansion'!AB19 -> 8279506.9 | Q15: ='1-Store Portland Expansion'!AC19 -> 8291653.3
K16: Equity Value | L16: =L14-L15 -> 1139204.6 | M16: =M14-M15 -> 1719893.3 | N16: =N14-N15 -> 2172579.4 | O16: =O14-O15 -> 2542077.1 | P16: =P14-P15 -> 2734215.9 | Q16: =Q14-Q15 -> 2832206.7
A17: D/E | B17: 1.8 | C17: 3.2 | D17: 0.2 | E17: 2.4 | F17: 0.9 | G17: 1 | H17: 0.3 | I17: 1.1
A18: Interest Bearing Debt ($) | B18: 2.7 | C18: 1.7 | D18: 0.1 | E18: 20.6 | F18: 1.4 | G18: 9.4 | H18: 3.9 | I18: 74.7 | K18: If 3-Store expansion in Seattle
A19: Shareholders Equity ($) | B19: 1.5 | C19: 0.5 | D19: 0.3 | E19: 8.5 | F19: 1.5 | G19: 9.7 | H19: 13.6 | I19: 77.1 | K19: Projected Revenue | L19: ='3 and 3‐Store Seattle Expansion'!G30 -> 25855557 | M19: ='3 and 3‐Store Seattle Expansion'!H30 -> 41483057 | N19: ='3 and 3‐Store Seattle Expansion'!I30 -> 59273395 | O19: ='3 and 3‐Store Seattle Expansion'!J30 -> 76321037 | P19: ='3 and 3‐Store Seattle Expansion'!K30 -> 94233061 | Q19: ='3 and 3‐Store Seattle Expansion'!L30 -> 1.0927136e+08
A20: Bond Rating | B20: na | C20: na | D20: na | E20: Baa | F20: na | G20: na | H20: na | I20: AA | K20: EV | L20: =L19*$P$6 -> 13972861 | M20: =M19*$P$6 -> 22418275 | N20: =N19*$P$6 -> 32032530 | O20: =O19*$P$6 -> 41245417 | P20: =P19*$P$6 -> 50925434 | Q20: =Q19*$P$6 -> 59052434
K21: Net Debt | L21: ='3 and 3‐Store Seattle Expansion'!G75 -> 3592727.5 | M21: ='3 and 3‐Store Seattle Expansion'!H75 -> 8970373.4 | N21: ='3 and 3‐Store Seattle Expansion'!I75 -> 9374559.6 | O21: ='3 and 3‐Store Seattle Expansion'!J75 -> 9750139.2 | P21: ='3 and 3‐Store Seattle Expansion'!K75 -> 10120070 | Q21: ='3 and 3‐Store Seattle Expansion'!L75 -> 10406806
A22: Beta coefficient | B22: 1.1 | C22: 0.3 | D22: 0.6 | E22: 0.8 | F22: 0.8 | G22: 0.5 | H22: 0.2 | I22: 0.7 | K22: Equity Value | L22: =L20-L21 -> 10380133 | M22: =M20-M21 -> 13447902 | N22: =N20-N21 -> 22657971 | O22: =O20-O21 -> 31495278 | P22: =P20-P21 -> 40805364 | Q22: =Q20-Q21 -> 48645628
A23: Ent. Value to EBITDA | B23: 39 | C23: 10.5 | D23: 4.7 | E23: 7.3 | F23: 12.5 | G23: 11.7 | H23: 5.9 | I23: 12.6
A24: Price / Sales | B24: 4.5 | C24: 0.4 | D24: 0.2 | E24: 0.2 | F24: 0.7 | G24: 0.6 | H24: 0.4 | I24: 0.7 | K24: Share price becuase of VC Investment
A25: WACC, % (2019) | B25: 0.086 | C25: 0.037 | D25: 0.053 | E25: 0.054 | F25: 0.062 | G25: 0.043 | H25: 0.016 | I25: 0.053 | K25: New Equity Investment | L25: 12000000
K26: New Shares Issued | L26: 11146367
K27: Share price | L27: =L25/L26 -> 1.076584
E28: Calculation of Relevent Industry WACC | K28: Total shares outstanding after the VC investment | L28: 42859839
E29: Relevent Competitor | F29: CASY | G29: ANCUF | H29: ANCADRNY | K29: Total Valution | L29: =L28*L27 -> 46142215
F30: C-Store | G30: C-Store | H30: C-Store
A31: Data Given | E31: Beta coefficient | F31: =F22 -> 0.8 | G31: =G22 -> 0.5 | H31: =H22 -> 0.2
A32: Risk Free Rate (Rf) | B32: 0.018 | E32: D/E | F32: =F17 -> 0.9 | G32: =G17 -> 1 | H32: =H17 -> 0.3 | L32: Pre-Vc | M32: Post Vc
A33: Market Risk Premimum (Rm-Rf) | B33: 0.059 | D33: Step-1 | E33: Beta_Asset | F33: =F31/(1+(1-B35)*F32) -> 0.48703275 | G33: =G31/(1+(1-E48)*G32) -> 0.25 | H33: =H31/(1+(1-F48)*H32) -> 0.15384615 | K33: Sedlar share number | L33: 5323542 | M33: 5323542
A34: Industry Beta (ß) | B34: 0.59 | E34: AV. D/E | F34: =AVERAGE(F32:H32) -> 0.73333333 | K34: Percentage | L34: =L33/16719551 -> 0.31840221 | M34: =M33/L28 -> 0.12420817
A35: Tax Rate | B35: =21%+7.6% -> 0.286 | C35: Oregon Tax Rates & Rankings | Tax Foundation | E35: Av. Beta_Asset | F35: =AVERAGE(F33:H33) -> 0.29695964 | K35: Price of total owner ship by Equity value (2025) | L35: =Q16*L34 -> 901780.86 | M35: =Q22*M34 -> 6042184.2
A36: Equity € | B36: =' Green Zebra Historic Data'!E37 -> 9173230 | D36: Step-2 | E36: Industry Average Levered Beta | F36: =F35/(1+(1-B35)*F34) -> 0.19490656
A37: Debt (D) | B37: =' Green Zebra Historic Data'!E36 -> 8543497
E38: Industry Cost of Equity | F38: =B32+F36*B33 -> 0.029499487
E39: WACC, % (2019) | F39: =F25 -> 0.062 | G39: =G25 -> 0.043 | H39: =H25 -> 0.016
A40: WACC Calculation of GZ | E40: E/V | F40: =1/(1+F32) -> 0.52631579 | G40: =1/(1+G32) -> 0.5 | H40: =1/(1+H32) -> 0.76923077
A41: Total Capital (E+D) | B41: =B36+B37 -> 17716727 | E41: D/V | F41: =F32/(1+F32) -> 0.47368421 | G41: =G32/(1+G32) -> 0.5 | H41: =H32/(1+H32) -> 0.23076923
A42: Weight of Equity (We) | B42: =B36/B41 -> 0.51777227 | E42: Cost of debt | F42: =(F39-F40*$F$38)/(F41*(1-B35)) -> 0.13741132 | G42: =(G39-G40*$F$38)/(G41*(1-B35)) -> 0.079132371 | H42: =(H39-H40*$F$38)/(H41*(1-B35)) -> -0.040613852
A43: Weight of Debt (D) | B43: =B37/B41 -> 0.48222773 | E43: Industry Cost of Debt | F43: =AVERAGE(F42:H42) -> 0.058643279
A44: Levered Beta | B44: =B34/(1+(1-B35)*(B37/B36)) -> 0.35435763 | E44: Av. E/V | F44: =AVERAGE(F40:H40) -> 0.59851552
A45: Cost of Equity Return (Re) | B45: =B32+B44*B33 -> 0.0389071 | E45: AV. D/V | F45: =AVERAGE(F41:H41) -> 0.40148448
A46: Industry Average Cost of Debt | B46: =F43 -> 0.058643279 | E46: Industry WACC | F46: =F44*F38+F45*(1-28.6%)*F43 -> 0.034466578
A47: WACC | B47: =(B42*B45)+(B43*B46) -> 0.048424433
I48: WACC to kon yaer ta nibo as a discount rate hisabe?
C106: Calculation of Pre-Money Valution
C107: Per Share Price | D107: =12000000/11146367 -> 1.076584
C108: Pre-Money Valuation | D108: =D107*16719551 -> 18000001

Sheet 3‐Store Seattle Expan 
F2: Depreciation
B3: 1-Store Seattle Expansion | C3: 1250000 | D3: =C3*3 -> 3750000 | F3: =D3/5 -> 750000
B4: pre-opening costs | C4: 94100
B5: advertasement | C5: 7700
B6: working capital 1% next year revenue | C6: =C14*1% -> 45000
B7: Site selection | C7: =100000/3 -> 33333.333
B8: Total up front cost for 1 store | C8: =SUM(C3:C7) -> 1430133.3
B9: Total up front cost is x3 | C9: =C8*3 -> 4290400 | D9: needed | G9: Year | H9: Payroll & Benefits | I9: Occupancy & Other | J9: Advertising & Marketing | K9: Total Operating Expenses of sale
D10: interest rate | E10: 0.125 | G10: 1 | H10: 0.189 | I10: 0.115 | J10: 0.01 | K10: 0.314
G11: 2 | H11: 0.187 | I11: 0.115 | J11: 0.01 | K11: 0.312
A12: Other given data | G12: 3 | H12: 0.185 | I12: 0.115 | J12: 0.01 | K12: 0.31
B13: Item | C13: Value / Rate | G13: 4 | H13: 0.183 | I13: 0.115 | J13: 0.01 | K13: 0.308
B14: 2020 Sales (4 total stores) | C14: 4500000 | G14: 5 | H14: 0.181 | I14: 0.115 | J14: 0.01 | K14: 0.306
B15: Sales Growth (2021–2025) | C15: in 2020 4.5M, then +10%, +10%, +5%, +2%, +1% | G15: 6 | H15: 0.18 | I15: 0.115 | J15: 0.01 | K15: 0.305
B16: COGS (% Sales) | C16: 60%, 59% , 59% , 58.50% , 58.50% , 58% | L16: {=TRANSPOSE(K10:K15)} -> 0.314 | M16: 0.312 | N16: 0.31 | O16: 0.308 | P16: 0.306 | Q16: 0.305
B17: Operating Expenses | C17: 31.40% , 31.20% , 31.00% , 30.80% , 30.60% , 30.50%
B20: Depreciation (2020-25)
B21: Interest Expense Rate
B22: State Tax | C22: 15,000 per year (minimum) AND 28.6% if pofitable (7.6% state and 21% federal tax) | G22: =G25*G27+' Green Zebra Historic Data'!M100+' Green Zebra Historic Data'!M102+' Green Zebra Historic Data'!M103 -> 9218289.5
B23: Forecast year | C23: 2020–2025
F25: 3 store expantion sale | G25: 13500000 | H25: 14850000 | I25: 16335000 | J25: 17151750 | K25: 18009338 | L25: 18189431
F26: cogs | H26: 0.6 | I26: 0.59 | J26: 0.59 | K26: 0.585 | L26: 0.58
F27: Total Operating Expenses of sale | G27: =L16 -> 0.314 | H27: =M16 -> 0.312 | I27: =N16 -> 0.31 | J27: =O16 -> 0.308 | K27: =P16 -> 0.306 | L27: =Q16 -> 0.305
B28: Working Capital (WC) Assumptions from exibit 7: | F28: Income Statement (2020-2025):
F29: Item | G29: 2020 | H29: 2021 | I29: 2022 | J29: 2023 | K29: 2024 | L29: 2025
B30: Cash: 2% of sales. | F30: Sales | G30: =C14*3 -> 13500000 | H30: =Table819[[#This Row],[2020]]+Table819[[#This Row],[2020]]*10% -> 14850000 | I30: =Table819[[#This Row],[2021]]+Table819[[#This Row],[2021]]*10% -> 16335000 | J30: =Table819[[#This Row],[2022]]+Table819[[#This Row],[2022]]*5% -> 17151750 | K30: =Table819[[#This Row],[2023]]+Table819[[#This Row],[2023]]*5% -> 18009338 | L30: =Table819[[#This Row],[2024]]+Table819[[#This Row],[2024]]*1% -> 18189431
B31: Inventory: 6.3% of COGS. | F31: COGS | G31: =G25*60% -> 8100000 | H31: =H25*60% -> 8910000 | I31: =I25*59% -> 9637650 | J31: =J25*59% -> 10119532 | K31: =K25*58.5% -> 10535463 | L31: =L25*58% -> 10549870 | M31: 3 store and existing 3 store have different cogs
B32: Accounts Payable: 7% of COGS. | F32: Gross Profit | G32: =G30-G31 -> 5400000 | H32: =H30-H31 -> 5940000 | I32: =I30-I31 -> 6697350 | J32: =J30-J31 -> 7032217.5 | K32: =K30-K31 -> 7473874.8 | L32: =L30-L31 -> 7639560.9
B33: Other Current Liabilities: 1.9% of sales. | F33: Operating Expenses | G33: =G25*G27 -> 4239000 | H33: =H25*H27 -> 4633200 | I33: =I25*I27 -> 5063850 | J33: =J25*J27 -> 5282739 | K33: =K25*K27 -> 5510857.4 | L33: =L25*L27 -> 5547776.5
F34: EBITDA | G34: =G32-G33 -> 1161000 | H34: =H32-H33 -> 1306800 | I34: =I32-I33 -> 1633500 | J34: =J32-J33 -> 1749478.5 | K34: =K32-K33 -> 1963017.3 | L34: =L32-L33 -> 2091784.4
F35: Depreciation | G35: =$F$3+' Green Zebra Historic Data'!M105 -> 1170072 | H35: =$F$3+' Green Zebra Historic Data'!N105 -> 1152711 | I35: =$F$3+' Green Zebra Historic Data'!O105 -> 1076661 | J35: =$F$3+' Green Zebra Historic Data'!P105 -> 1061583 | K35: =$F$3+' Green Zebra Historic Data'!Q105 -> 1012919 | L35: =$F$3+' Green Zebra Historic Data'!R105 -> 875551
F36: EBIT | G36: =G34-G35 -> -9072 | H36: =H34-H35 -> 154089 | I36: =I34-I35 -> 556839 | J36: =J34-J35 -> 687895.5 | K36: =K34-K35 -> 950098.34 | L36: =L34-L35 -> 1216233.4
F37: Interest Expense | G37: =' Green Zebra Historic Data'!$P$19 -> 433114 | H37: =' Green Zebra Historic Data'!$P$19 -> 433114 | I37: =' Green Zebra Historic Data'!$P$19 -> 433114 | J37: =' Green Zebra Historic Data'!$P$19 -> 433114 | K37: =' Green Zebra Historic Data'!$P$19 -> 433114 | L37: =' Green Zebra Historic Data'!$P$19 -> 433114 | M37: no new loan taken and no information about interest
F38: EBT | G38: =G36-G37 -> -442186 | H38: =H36-H37 -> -279025 | I38: =I36-I37 -> 123725 | J38: =J36-J37 -> 254781.5 | K38: =K36-K37 -> 516984.34 | L38: =L36-L37 -> 783119.44
F39: Tax | G39: 15000 | H39: 15000 | I39: 15000 | J39: 15000 | K39: 15000 | L39: 15000 | M39: As 2021 income alone higher than all the loss made in past, taxed only amunt remaining loss - income2021 | O39: total loss | P39: 2021 ebit - total previous loss
F40: Net Income | G40: =G38-G39 -> -457186 | H40: =H38-H39 -> -294025 | I40: =I38-I39 -> 108725 | J40: =J38-J39 -> 239781.5 | K40: =K38-K39 -> 501984.34 | L40: =L38-L39 -> 768119.44 | O40: =SUM(Table819[[#This Row],[2020]:[2021]]) -> -751211 | P40: =H38+I38+J38 -> 99481.5
F43: Cash Flow Statement (2020-2025):
F44: Item | G44: 2020 | H44: 2021 | I44: 2022 | J44: 2023 | K44: 2024 | L44: 2025
F45: Net Income | G45: =G40 -> -457186 | H45: =H40 -> -294025 | I45: =I40 -> 108725 | J45: =J40 -> 239781.5 | K45: =K40 -> 501984.34 | L45: =L40 -> 768119.44
F46: Adjustments for:
F47: - Depreciation | G47: =G35 -> 1170072 | H47: =H35 -> 1152711 | I47: =I35 -> 1076661 | J47: =J35 -> 1061583 | K47: =K35 -> 1012919 | L47: =L35 -> 875551
F48: Changes in Working Capital:
F49: - Inventories | G49: =G66 -> 510300 | H49: =H66 -> 561330 | I49: =I66 -> 607171.95 | J49: =J66 -> 637530.55 | K49: =K66 -> 663734.15 | L49: =L66 -> 664641.81
F50: + Accounts Payable | G50: =G71 -> 567000 | H50: =H71 -> 623700 | I50: =I71 -> 674635.5 | J50: =J71 -> 708367.28 | K50: =K71 -> 737482.39 | L50: =L71 -> 738490.9
F51: Cash from Operations | G51: =G45+G47-G49+G50 -> 769586 | H51: =H45+H47-H49+H50 -> 921056 | I51: =I45+I47-I49+I50 -> 1252849.6 | J51: =J45+J47-J49+J50 -> 1372201.2 | K51: =K45+K47-K49+K50 -> 1588651.6 | L51: =L45+L47-L49+L50 -> 1717519.5
F52: Cash from Investing:
F53: - Capital Expenditures | G53: =-C9 -> -4290400 | H53: 0 | I53: 0 | J53: 0 | K53: 0 | L53: 0
F54: Cash from Financing:
F55: - VC Investment | G55: 12000000 | H55: 0 | I55: 0 | J55: 0 | K55: 0 | L55: 0
F56: Net Increase in Cash | G56: =G51+G53+G55 -> 8479186 | H56: =H51+H53+H55 -> 921056 | I56: =I51+I53+I55 -> 1252849.6 | J56: =J51+J53+J55 -> 1372201.2 | K56: =K51+K53+K55 -> 1588651.6 | L56: =L51+L53+L55 -> 1717519.5
F57: Net cash flow | G57: 991610 | H57: =G58 -> 9470796 | I57: =H58 -> 10391852 | J57: =I58 -> 11644702 | K57: =J58 -> 13016903 | L57: =K58 -> 14605554
F58: Closing Cash Balance | G58: =G56+G57 -> 9470796 | H58: =H56+H57 -> 10391852 | I58: =I56+I57 -> 11644702 | J58: =J56+J57 -> 13016903 | K58: =K56+K57 -> 14605554 | L58: =L56+L57 -> 16323074
C59: EFN
F62: Balance Sheet for 3 Stores in Seattle (2020-2025):
F63: Item | G63: 2020 | H63: 2021 | I63: 2022 | J63: 2023 | K63: 2024 | L63: 2025
F64: Assets
F65: - Cash & Equivalents | G65: =G30*2% -> 270000 | H65: =H30*2% -> 297000 | I65: =I30*2% -> 326700 | J65: =J30*2% -> 343035 | K65: =K30*2% -> 360186.75 | L65: =L30*2% -> 363788.62
F66: - Inventory | G66: =G31*6.3% -> 510300 | H66: =H31*6.3% -> 561330 | I66: =I31*6.3% -> 607171.95 | J66: =J31*6.3% -> 637530.55 | K66: =K31*6.3% -> 663734.15 | L66: =L31*6.3% -> 664641.81
F67: Total Current Assets | G67: =G65+G66 -> 780300 | H67: =H65+H66 -> 858330 | I67: =I65+I66 -> 933871.95 | J67: =J65+J66 -> 980565.55 | K67: =K65+K66 -> 1023920.9 | L67: =L65+L66 -> 1028430.4
F68: - Fixed Assets (net) | G68: =G30*'1-Store Portland Expansion'!S2 -> 2524500 | H68: =G68-$F$3 -> 1774500 | I68: =H68-$F$3 -> 1024500 | J68: =I68-$F$3 -> 274500 | K68: =J68-$F$3 -> -475500 | L68: =K68-$F$3 -> -1225500
F69: Total Assets | G69: =G67+G68 -> 3304800 | H69: =H67+H68 -> 2632830 | I69: =I67+I68 -> 1958371.9 | J69: =J67+J68 -> 1255065.5 | K69: =K67+K68 -> 548420.9 | L69: =L67+L68 -> -197069.57
F70: Liabilities
F71: - Accounts Payable | G71: =G31*7% -> 567000 | H71: =H31*7% -> 623700 | I71: =I31*7% -> 674635.5 | J71: =J31*7% -> 708367.28 | K71: =K31*7% -> 737482.39 | L71: =L31*7% -> 738490.9
F72: - Other Current Liabilities | G72: =G30*1.9% -> 256500 | H72: =H30*1.9% -> 282150 | I72: =I30*1.9% -> 310365 | J72: =J30*1.9% -> 325883.25 | K72: =K30*1.9% -> 342177.41 | L72: =L30*1.9% -> 345599.19
F73: Total Current Liabilities | G73: =G71+G72 -> 823500 | H73: =H71+H72 -> 905850 | I73: =I71+I72 -> 985000.5 | J73: =J71+J72 -> 1034250.5 | K73: =K71+K72 -> 1079659.8 | L73: =L71+L72 -> 1084090.1
F74: - Long Term Debt | G74: =' Green Zebra Historic Data'!$E$35 - 5000000 -> 2019863 | H74: =' Green Zebra Historic Data'!$E$35 -> 7019863 | I74: =' Green Zebra Historic Data'!$E$35 -> 7019863 | J74: =' Green Zebra Historic Data'!$E$35 -> 7019863 | K74: =' Green Zebra Historic Data'!$E$35 -> 7019863 | L74: =' Green Zebra Historic Data'!$E$35 -> 7019863
F75: Total Liabilities | G75: =G74+G73 -> 2843363 | H75: =H74+H73 -> 7925713 | I75: =I74+I73 -> 8004863.5 | J75: =J74+J73 -> 8054113.5 | K75: =K74+K73 -> 8099522.8 | L75: =L74+L73 -> 8103953.1
F76: Equity
F77: - Shareholder's Equity | G77: =' Green Zebra Historic Data'!$P$48 + G55 + 5000000 -> 26173230 | H77: =' Green Zebra Historic Data'!$P$48 + '3‐Store Seattle Expan '!$G$55 + 5000000 -> 26173230 | I77: =' Green Zebra Historic Data'!$P$48 + '3‐Store Seattle Expan '!$G$55 + 5000000 -> 26173230 | J77: =' Green Zebra Historic Data'!$P$48 + '3‐Store Seattle Expan '!$G$55 + 5000000 -> 26173230 | K77: =' Green Zebra Historic Data'!$P$48 + '3‐Store Seattle Expan '!$G$55 + 5000000 -> 26173230 | L77: =' Green Zebra Historic Data'!$P$48 + '3‐Store Seattle Expan '!$G$55 + 5000000 -> 26173230
F78: - Retained Earnings | G78: =' Green Zebra Historic Data'!P49 + G79 -> -11053876 | H78: =G78+H40 -> -11347901 | I78: =H78+I40 -> -11239176 | J78: =I78+J40 -> -10999394 | K78: =J78+K40 -> -10497410 | L78: =K78+L40 -> -9729290.7
F79: - Current Year Earnings | G79: =G40 -> -457186 | H79: =H40 -> -294025 | I79: =I40 -> 108725 | J79: =J40 -> 239781.5 | K79: =K40 -> 501984.34 | L79: =L40 -> 768119.44
F80: Total Net Equity | G80: =SUM(G77:G79) -> 14662168 | H80: =SUM(H77:H79) -> 14531304 | I80: =SUM(I77:I79) -> 15042779 | J80: =SUM(J77:J79) -> 15413617 | K80: =SUM(K77:K79) -> 16177804 | L80: =SUM(L77:L79) -> 17212059
F81: Total Liab & Equity | G81: =SUM(G75+G80) -> 17505531 | H81: =SUM(H75+H80) -> 22457017 | I81: =SUM(I75+I80) -> 23047642 | J81: =SUM(J75+J80) -> 23467731 | K81: =SUM(K75+K80) -> 24277327 | L81: =SUM(L75+L80) -> 25316012
F82: Assets - (Liab + Equity)
F83: EFN | G83: =G81-G69 -> 14200731 | H83: =H81-H69 -> 19824187 | I83: =I81-I69 -> 21089271 | J83: =J81-J69 -> 22212665 | K83: =K81-K69 -> 23728906 | L83: =L81-L69 -> 25513081
F86: Amdr seattle expension er sudhu data ase ar opposite a Portland er data 4ta store er combined a, tahole NPV comparision korbo kmne?

Sheet 3 and 3‐Store Seattle Expansion
F2: Depreciation
B3: 1-Store Seattle Expansion | C3: 1250000 | D3: =C3*3 -> 3750000 | F3: =D3/5 -> 750000
B4: pre-opening costs | C4: 94100
B5: advertasement | C5: 7700
B6: working capital 1% next year revenue | C6: =C14*1% -> 45000
B7: Site selection | C7: =100000/3 -> 33333.333
B8: Total up front cost for 1 store | C8: =SUM(C3:C7) -> 1430133.3
B9: Total up front cost is x3 | C9: =C8*3 -> 4290400 | D9: needed | G9: Year | H9: Payroll & Benefits | I9: Occupancy & Other | J9: Advertising & Marketing | K9: Total Operating Expenses of sale
D10: interest rate | E10: 0.125 | G10: 1 | H10: 0.189 | I10: 0.115 | J10: 0.01 | K10: 0.314
G11: 2 | H11: 0.187 | I11: 0.115 | J11: 0.01 | K11: 0.312
A12: Other given data | G12: 3 | H12: 0.185 | I12: 0.115 | J12: 0.01 | K12: 0.31
B13: Item | C13: Value / Rate | G13: 4 | H13: 0.183 | I13: 0.115 | J13: 0.01 | K13: 0.308
B14: 2020 Sales (4 total stores) | C14: 4500000 | G14: 5 | H14: 0.181 | I14: 0.115 | J14: 0.01 | K14: 0.306
B15: Sales Growth (2021–2025) | C15: in 2020 4.5M, then +10%, +10%, +5%, +2%, +1% | G15: 6 | H15: 0.18 | I15: 0.115 | J15: 0.01 | K15: 0.305
B16: COGS (% Sales) | C16: 60%, 59% , 59% , 58.50% , 58.50% , 58% | L16: {=TRANSPOSE(K10:K15)} -> 0.314 | M16: 0.312 | N16: 0.31 | O16: 0.308 | P16: 0.306 | Q16: 0.305
B17: Operating Expenses | C17: 31.40% , 31.20% , 31.00% , 30.80% , 30.60% , 30.50%
B20: Depreciation (2020-25)
B21: Interest Expense Rate
B22: State Tax | C22: 15,000 per year (minimum) AND 28.6% if pofitable (7.6% state and 21% federal tax) | G22: =G25*G27+' Green Zebra Historic Data'!M100+' Green Zebra Historic Data'!M102+' Green Zebra Historic Data'!M103 -> 9218289.5
B23: Forecast year | C23: 2020–2025
F25: 3 store expantion sale | G25: 13500000 | H25: 14850000 | I25: 16335000 | J25: 17151750 | K25: 18009338 | L25: 18189431
F26: cogs | H26: 0.6 | I26: 0.59 | J26: 0.59 | K26: 0.585 | L26: 0.58
F27: Total Operating Expenses of sale | G27: =L16 -> 0.314 | H27: =M16 -> 0.312 | I27: =N16 -> 0.31 | J27: =O16 -> 0.308 | K27: =P16 -> 0.306 | L27: =Q16 -> 0.305
B28: Working Capital (WC) Assumptions from exibit 7: | F28: Income Statement (2020-2025):
F29: Item | G29: 2020 | H29: 2021 | I29: 2022 | J29: 2023 | K29: 2024 | L29: 2025
B30: Cash: 2% of sales. | F30: Sales | G30: =C14*3 + ' Green Zebra Historic Data'!N66 -> 25855557 | H30: =Table8[[#This Row],[2020]]+Table8[[#This Row],[2020]]*10%+' Green Zebra Historic Data'!O66 -> 41483057 | I30: =Table8[[#This Row],[2021]]+Table8[[#This Row],[2021]]*10%+' Green Zebra Historic Data'!P66 -> 59273395 | J30: =Table8[[#This Row],[2022]]+Table8[[#This Row],[2022]]*5%+' Green Zebra Historic Data'!Q66 -> 76321037 | K30: =Table8[[#This Row],[2023]]+Table8[[#This Row],[2023]]*5%+' Green Zebra Historic Data'!R66 -> 94233061 | L30: =Table8[[#This Row],[2024]]+Table8[[#This Row],[2024]]*1%+' Green Zebra Historic Data'!S66 -> 1.0927136e+08
B31: Inventory: 6.3% of COGS. | F31: COGS | G31: =G25*60% + ' Green Zebra Historic Data'!N66*'1-Store Portland Expansion'!G9 -> 15451556 | H31: =H25*60% + ' Green Zebra Historic Data'!O66*'1-Store Portland Expansion'!H9 -> 16604747 | I31: =I25*59% + ' Green Zebra Historic Data'!P66*'1-Store Portland Expansion'!I9 -> 17550029 | J31: =J25*59% + ' Green Zebra Historic Data'!Q66*'1-Store Portland Expansion'!J9 -> 18288236 | K31: =K25*58.5% + ' Green Zebra Historic Data'!R66*'1-Store Portland Expansion'!K9 -> 18711126 | L31: =L25*58% + ' Green Zebra Historic Data'!S66*'1-Store Portland Expansion'!L9 -> 18725534 | M31: 3 store and existing 3 store have different cogs
B32: Accounts Payable: 7% of COGS. | F32: Gross Profit | G32: =G30-G31 -> 10404001 | H32: =H30-H31 -> 24878310 | I32: =I30-I31 -> 41723366 | J32: =J30-J31 -> 58032801 | K32: =K30-K31 -> 75521935 | L32: =L30-L31 -> 90545830
B33: Other Current Liabilities: 1.9% of sales. | F33: Operating Expenses | G33: =G25*G27+' Green Zebra Historic Data'!M100+' Green Zebra Historic Data'!M102+' Green Zebra Historic Data'!M103 -> 9218289.5 | H33: =H25*H27+' Green Zebra Historic Data'!N100+' Green Zebra Historic Data'!N102+' Green Zebra Historic Data'!N103 -> 9784767.9 | I33: =I25*I27+' Green Zebra Historic Data'!O100+' Green Zebra Historic Data'!O102+' Green Zebra Historic Data'!O103 -> 10316033 | J33: =J25*J27+' Green Zebra Historic Data'!P100+' Green Zebra Historic Data'!P102+' Green Zebra Historic Data'!P103 -> 10592396 | K33: =K25*K27+' Green Zebra Historic Data'!Q100+' Green Zebra Historic Data'!Q102+' Green Zebra Historic Data'!Q103 -> 10768655 | L33: =L25*L27+' Green Zebra Historic Data'!R100+' Green Zebra Historic Data'!R102+' Green Zebra Historic Data'!R103 -> 10805574
F34: EBITDA | G34: =G32-G33 -> 1185711.1 | H34: =H32-H33 -> 15093542 | I34: =I32-I33 -> 31407334 | J34: =J32-J33 -> 47440404 | K34: =K32-K33 -> 64753280 | L34: =L32-L33 -> 79740256
F35: Depreciation | G35: =$F$3+' Green Zebra Historic Data'!M105 -> 1170072 | H35: =$F$3+' Green Zebra Historic Data'!N105 -> 1152711 | I35: =$F$3+' Green Zebra Historic Data'!O105 -> 1076661 | J35: =$F$3+' Green Zebra Historic Data'!P105 -> 1061583 | K35: =$F$3+' Green Zebra Historic Data'!Q105 -> 1012919 | L35: =$F$3+' Green Zebra Historic Data'!R105 -> 875551
F36: EBIT | G36: =G34-G35 -> 15639.114 | H36: =H34-H35 -> 13940831 | I36: =I34-I35 -> 30330673 | J36: =J34-J35 -> 46378821 | K36: =K34-K35 -> 63740361 | L36: =L34-L35 -> 78864705
F37: Interest Expense | G37: =' Green Zebra Historic Data'!$P$19 -> 433114 | H37: =' Green Zebra Historic Data'!$P$19 -> 433114 | I37: =' Green Zebra Historic Data'!$P$19 -> 433114 | J37: =' Green Zebra Historic Data'!$P$19 -> 433114 | K37: =' Green Zebra Historic Data'!$P$19 -> 433114 | L37: =' Green Zebra Historic Data'!$P$19 -> 433114 | M37: no new loan taken and no information about interest
F38: EBT | G38: =G36-G37 -> -417474.89 | H38: =H36-H37 -> 13507717 | I38: =I36-I37 -> 29897559 | J38: =J36-J37 -> 45945707 | K38: =K36-K37 -> 63307247 | L38: =L36-L37 -> 78431591
F39: Tax | G39: 15000 | H39: =P40*28.6% -> 2319560.9 | I39: =I38*28.6% -> 8550701.7 | J39: =J38*28.6% -> 13140472 | K39: =K38*28.6% -> 18105873 | L39: =L38*28.6% -> 22431435 | M39: As 2021 income alone higher than all the loss made in past, taxed only amunt remaining loss - income2021 | O39: total loss | P39: 2021 ebit - total previous loss
F40: Net Income | G40: =G38-G39 -> -432474.89 | H40: =H38-H39 -> 11188156 | I40: =I38-I39 -> 21346857 | J40: =J38-J39 -> 32805235 | K40: =K38-K39 -> 45201374 | L40: =L38-L39 -> 56000156 | O40: =SUM(' Green Zebra Historic Data'!N25:P25)-Table8[[#This Row],[2020]] -> -5397364.1 | P40: =H38+O40 -> 8110352.7
F43: Cash Flow Statement (2020-2025):
F44: Item | G44: 2020 | H44: 2021 | I44: 2022 | J44: 2023 | K44: 2024 | L44: 2025
F45: Net Income | G45: =G40 -> -432474.89 | H45: =H40 -> 11188156 | I45: =I40 -> 21346857 | J45: =J40 -> 32805235 | K45: =K40 -> 45201374 | L45: =L40 -> 56000156
F46: Adjustments for:
F47: - Depreciation | G47: =G35 -> 1170072 | H47: =H35 -> 1152711 | I47: =I35 -> 1076661 | J47: =J35 -> 1061583 | K47: =K35 -> 1012919 | L47: =L35 -> 875551
F48: Changes in Working Capital:
F49: - Inventories | G49: =G66 -> 973448.05 | H49: =H66 -> 1046099.1 | I49: =I66 -> 1105651.8 | J49: =J66 -> 1152158.9 | K49: =K66 -> 1178801 | L49: =L66 -> 1179708.6
F50: + Accounts Payable | G50: =G71 -> 1081608.9 | H50: =H71 -> 1162332.3 | I50: =I71 -> 1228502 | J50: =J71 -> 1280176.5 | K50: =K71 -> 1309778.9 | L50: =L71 -> 1310787.4
F51: Cash from Operations | G51: =G45+G47-G49+G50 -> 845758.01 | H51: =H45+H47-H49+H50 -> 12457100 | I51: =I45+I47-I49+I50 -> 22546368 | J51: =J45+J47-J49+J50 -> 33994836 | K51: =K45+K47-K49+K50 -> 46345271 | L51: =L45+L47-L49+L50 -> 57006786
F52: Cash from Investing:
F53: - Capital Expenditures | G53: =-C9 -> -4290400 | H53: 0 | I53: 0 | J53: 0 | K53: 0 | L53: 0
F54: Cash from Financing:
F55: - VC Investment | G55: 12000000 | H55: 0 | I55: 0 | J55: 0 | K55: 0 | L55: 0
F56: Net Increase in Cash | G56: =G51+G53+G55 -> 8555358 | H56: =H51+H53+H55 -> 12457100 | I56: =I51+I53+I55 -> 22546368 | J56: =J51+J53+J55 -> 33994836 | K56: =K51+K53+K55 -> 46345271 | L56: =L51+L53+L55 -> 57006786
F57: Net cash flow | G57: 991610 | H57: =G58 -> 9546968 | I57: =H58 -> 22004068 | J57: =I58 -> 44550436 | K57: =J58 -> 78545272 | L57: =K58 -> 1.2489054e+08
F58: Closing Cash Balance | G58: =G56+G57 -> 9546968 | H58: =H56+H57 -> 22004068 | I58: =I56+I57 -> 44550436 | J58: =J56+J57 -> 78545272 | K58: =K56+K57 -> 1.2489054e+08 | L58: =L56+L57 -> 1.8189733e+08
C59: EFN
F62: Balance Sheet for 3 Stores in Seattle (2020-2025):
F63: Item | G63: 2020 | H63: 2021 | I63: 2022 | J63: 2023 | K63: 2024 | L63: 2025
F64: Assets
F65: - Cash & Equivalents | G65: =G30*2% -> 517111.14 | H65: =H30*2% -> 829661.13 | I65: =I30*2% -> 1185467.9 | J65: =J30*2% -> 1526420.7 | K65: =K30*2% -> 1884661.2 | L65: =L30*2% -> 2185427.3
F66: - Inventory | G66: =G31*6.3% -> 973448.05 | H66: =H31*6.3% -> 1046099.1 | I66: =I31*6.3% -> 1105651.8 | J66: =J31*6.3% -> 1152158.9 | K66: =K31*6.3% -> 1178801 | L66: =L31*6.3% -> 1179708.6
F67: Total Current Assets | G67: =G65+G66 -> 1490559.2 | H67: =H65+H66 -> 1875760.2 | I67: =I65+I66 -> 2291119.7 | J67: =J65+J66 -> 2678579.6 | K67: =K65+K66 -> 3063462.2 | L67: =L65+L66 -> 3365135.9
F68: - Fixed Assets (net) | G68: =G30*'1-Store Portland Expansion'!S2 -> 4834989.2 | H68: =G68-$F$3 -> 4084989.2 | I68: =H68-$F$3 -> 3334989.2 | J68: =I68-$F$3 -> 2584989.2 | K68: =J68-$F$3 -> 1834989.2 | L68: =K68-$F$3 -> 1084989.2
F69: Total Assets | G69: =G67+G68 -> 6325548.4 | H69: =H67+H68 -> 5960749.4 | I69: =I67+I68 -> 5626108.9 | J69: =J67+J68 -> 5263568.8 | K69: =K67+K68 -> 4898451.3 | L69: =L67+L68 -> 4450125.1
F70: Liabilities
F71: - Accounts Payable | G71: =G31*7% -> 1081608.9 | H71: =H31*7% -> 1162332.3 | I71: =I31*7% -> 1228502 | J71: =J31*7% -> 1280176.5 | K71: =K31*7% -> 1309778.9 | L71: =L31*7% -> 1310787.4
F72: - Other Current Liabilities | G72: =G30*1.9% -> 491255.58 | H72: =H30*1.9% -> 788178.08 | I72: =I30*1.9% -> 1126194.5 | J72: =J30*1.9% -> 1450099.7 | K72: =K30*1.9% -> 1790428.2 | L72: =L30*1.9% -> 2076155.9
F73: Total Current Liabilities | G73: =G71+G72 -> 1572864.5 | H73: =H71+H72 -> 1950510.4 | I73: =I71+I72 -> 2354696.6 | J73: =J71+J72 -> 2730276.2 | K73: =K71+K72 -> 3100207 | L73: =L71+L72 -> 3386943.3
F74: - Long Term Debt | G74: =' Green Zebra Historic Data'!$E$35 - 5000000 -> 2019863 | H74: =' Green Zebra Historic Data'!$E$35 -> 7019863 | I74: =' Green Zebra Historic Data'!$E$35 -> 7019863 | J74: =' Green Zebra Historic Data'!$E$35 -> 7019863 | K74: =' Green Zebra Historic Data'!$E$35 -> 7019863 | L74: =' Green Zebra Historic Data'!$E$35 -> 7019863
F75: Total Liabilities | G75: =G74+G73 -> 3592727.5 | H75: =H74+H73 -> 8970373.4 | I75: =I74+I73 -> 9374559.6 | J75: =J74+J73 -> 9750139.2 | K75: =K74+K73 -> 10120070 | L75: =L74+L73 -> 10406806
F76: Equity
F77: - Shareholder's Equity | G77: =' Green Zebra Historic Data'!$P$48 + G55 + 5000000 -> 26173230 | H77: =' Green Zebra Historic Data'!$P$48 + '3 and 3‐Store Seattle Expansion'!$G$55 + 5000000 -> 26173230 | I77: =' Green Zebra Historic Data'!$P$48 + '3 and 3‐Store Seattle Expansion'!$G$55 + 5000000 -> 26173230 | J77: =' Green Zebra Historic Data'!$P$48 + '3 and 3‐Store Seattle Expansion'!$G$55 + 5000000 -> 26173230 | K77: =' Green Zebra Historic Data'!$P$48 + '3 and 3‐Store Seattle Expansion'!$G$55 + 5000000 -> 26173230 | L77: =' Green Zebra Historic Data'!$P$48 + '3 and 3‐Store Seattle Expansion'!$G$55 + 5000000 -> 26173230
F78: - Retained Earnings | G78: =' Green Zebra Historic Data'!P49 + G79 -> -11029165 | H78: =G78+H40 -> 158991.09 | I78: =H78+I40 -> 21505848 | J78: =I78+J40 -> 54311083 | K78: =J78+K40 -> 99512457 | L78: =K78+L40 -> 1.5551261e+08
F79: - Current Year Earnings | G79: =G40 -> -432474.89 | H79: =H40 -> 11188156 | I79: =I40 -> 21346857 | J79: =J40 -> 32805235 | K79: =K40 -> 45201374 | L79: =L40 -> 56000156
F80: Total Net Equity | G80: =SUM(G77:G79) -> 14711590 | H80: =SUM(H77:H79) -> 37520377 | I80: =SUM(I77:I79) -> 69025935 | J80: =SUM(J77:J79) -> 1.1328955e+08 | K80: =SUM(K77:K79) -> 1.7088706e+08 | L80: =SUM(L77:L79) -> 2.37686e+08
F81: Total Liab & Equity | G81: =SUM(G75+G80) -> 18304318 | H81: =SUM(H75+H80) -> 46490750 | I81: =SUM(I75+I80) -> 78400494 | J81: =SUM(J75+J80) -> 1.2303969e+08 | K81: =SUM(K75+K80) -> 1.8100713e+08 | L81: =SUM(L75+L80) -> 2.4809281e+08
F82: Assets - (Liab + Equity)
F83: EFN | G83: =G69-G81 -> -11978769 | H83: =H69-H81 -> -40530001 | I83: =I69-I81 -> -72774385 | J83: =J69-J81 -> -1.1777612e+08 | K83: =K69-K81 -> -1.7610868e+08 | L83: =L69-L81 -> -2.4364268e+08
F86: Amdr seattle expension er sudhu data ase ar opposite a Portland er data 4ta store er combined a, tahole NPV comparision korbo kmne?

Sheet NPV and PI
A1: Seattle Expansion | D1: Free Cash Flow | K1: Portland Expansion
B2: + | C2: Ebit | D2: ='3‐Store Seattle Expan '!G36 -> -9072 | E2: ='3‐Store Seattle Expan '!H36 -> 154089 | F2: ='3‐Store Seattle Expan '!I36 -> 556839 | G2: ='3‐Store Seattle Expan '!J36 -> 687895.5 | H2: ='3‐Store Seattle Expan '!K36 -> 950098.34 | I2: ='3‐Store Seattle Expan '!L36 -> 1216233.4 | L2: + | M2: Ebit | N2: ='1-Store Portland Expansion'!G19 -> -385872 | O2: ='1-Store Portland Expansion'!H19 -> -128256 | P2: ='1-Store Portland Expansion'!I19 -> 345753.75 | Q2: ='1-Store Portland Expansion'!J19 -> 547570.93 | R2: ='1-Store Portland Expansion'!K19 -> 694937.73 | S2: ='1-Store Portland Expansion'!L19 -> 841884.3
B3: + | C3: Depreciation | D3: ='3 and 3‐Store Seattle Expansion'!G35 -> 1170072 | E3: ='3 and 3‐Store Seattle Expansion'!H35 -> 1152711 | F3: ='3 and 3‐Store Seattle Expansion'!I35 -> 1076661 | G3: ='3 and 3‐Store Seattle Expansion'!J35 -> 1061583 | H3: ='3 and 3‐Store Seattle Expansion'!K35 -> 1012919 | I3: ='3 and 3‐Store Seattle Expansion'!L35 -> 875551 | L3: + | M3: Depreciation | N3: ='1-Store Portland Expansion'!G18 -> 420072 | O3: ='1-Store Portland Expansion'!H18 -> 402711 | P3: ='1-Store Portland Expansion'!I18 -> 326661 | Q3: ='1-Store Portland Expansion'!J18 -> 311583 | R3: ='1-Store Portland Expansion'!K18 -> 262919 | S3: ='1-Store Portland Expansion'!L18 -> 125551
B4: - | C4: current assent - current liabilities | D4: ='3 and 3‐Store Seattle Expansion'!G67-'3 and 3‐Store Seattle Expansion'!G73 -> -82305.338 | E4: ='3 and 3‐Store Seattle Expansion'!H67-'3 and 3‐Store Seattle Expansion'!H73 -> -74750.172 | F4: ='3 and 3‐Store Seattle Expansion'!I67-'3 and 3‐Store Seattle Expansion'!I73 -> -63576.809 | G4: ='3 and 3‐Store Seattle Expansion'!J67-'3 and 3‐Store Seattle Expansion'!J73 -> -51696.617 | H4: ='3 and 3‐Store Seattle Expansion'!K67-'3 and 3‐Store Seattle Expansion'!K73 -> -36744.824 | I4: ='3 and 3‐Store Seattle Expansion'!L67-'3 and 3‐Store Seattle Expansion'!L73 -> -21807.373 | L4: - | M4: current assent - current liabilities | N4: ='1-Store Portland Expansion'!X10-'1-Store Portland Expansion'!X17 -> -74121.5 | O4: ='1-Store Portland Expansion'!Y10-'1-Store Portland Expansion'!Y17 -> -77269.61 | P4: ='1-Store Portland Expansion'!Z10-'1-Store Portland Expansion'!Z17 -> -78788.261 | Q4: ='1-Store Portland Expansion'!AA10-'1-Store Portland Expansion'!AA17 -> -81139.791 | R4: ='1-Store Portland Expansion'!AB10-'1-Store Portland Expansion'!AB17 -> -82362.587 | S4: ='1-Store Portland Expansion'!AC10-'1-Store Portland Expansion'!AC17 -> -82986.213
E5: ='3 and 3‐Store Seattle Expansion'!H53 -> 0 | F5: ='3 and 3‐Store Seattle Expansion'!I53 -> 0 | G5: ='3 and 3‐Store Seattle Expansion'!J53 -> 0 | H5: ='3 and 3‐Store Seattle Expansion'!K53 -> 0 | I5: ='3 and 3‐Store Seattle Expansion'!L53 -> 0 | O5: =-'1-Store Portland Expansion'!P37 -> 0 | P5: =-'1-Store Portland Expansion'!Q37 -> 0 | Q5: =-'1-Store Portland Expansion'!R37 -> 0 | R5: =-'1-Store Portland Expansion'!S37 -> 0 | S5: =-'1-Store Portland Expansion'!T37 -> 0
C6: Free Cash Flow | D6: =D2+D3--D5--D4 -> 1078694.7 | E6: =E2+E3--E5--E4 -> 1232049.8 | F6: =F2+F3--F5--F4 -> 1569923.2 | G6: =G2+G3--G5--G4 -> 1697781.9 | H6: =H2+H3--H5--H4 -> 1926272.5 | I6: =I2+I3--I5--I4 -> 2069977.1 | M6: Free Cash Flow | N6: =N2+N3--N5--N4 -> -39921.5 | O6: =O2+O3--O5--O4 -> 197185.39 | P6: =P2+P3--P5--P4 -> 593626.49 | Q6: =Q2+Q3--Q5--Q4 -> 778014.14 | R6: =R2+R3--R5--R4 -> 875494.15 | S6: =S2+S3--S5--S4 -> 884449.09
C9: WACC | D9: ='GZ Competitors AND WACC'!B47 -> 0.048424433
M10: NPV for Portland
C11: NPV for 3 Store Seattle Expansion | M11: Year | N11: Cash Flow
C12: Year | D12: Cash Flow | M12: 0 | N12: =-'1-Store Portland Expansion'!O37 -> -920000
C13: 0 | D13: ='3 and 3‐Store Seattle Expansion'!G53 -> -4290400 | M13: 1 | N13: {=TRANSPOSE(N6:S6)} -> -39921.5
C14: 1 | D14: {=TRANSPOSE(D6:I6)} -> 1078694.7 | M14: 2 | N14: 197185.39
C15: 2 | D15: 1232049.8 | M15: 3 | N15: 593626.49
C16: 3 | D16: 1569923.2 | M16: 4 | N16: 778014.14
C17: 4 | D17: 1697781.9 | M17: 5 | N17: 875494.15
C18: 5 | D18: 1926272.5 | M18: 6 | N18: 884449.09
C19: 6 | D19: 2069977.1 | M19: NPV | N19: =NPV(D9,N13:N18)+N12 -> 1737461.4
C20: NPV | D20: =NPV(D9,D14:D19)+D13 -> 3706094.1 | M20: IRR | N20: =IRR(N12:N19) -> 0.40527088
C21: IRR | D21: =IRR(D13:D19) -> 0.25305503
C23: Pay back time:
C28: Expansion | D28: Initial Investment | E28: NPV | F28: Profitability Index
C29: Seattel | D29: =-D13 -> 4290400 | E29: =D20 -> 3706094.1 | F29: =E29/D29 -> 0.86381086
C30: Pordland | D30: =-N12 -> 920000 | E30: =N19 -> 1737461.4 | F30: =E30/D30 -> 1.888545
C41: NPV te amra free cashflow e to nibo??? - balance sheet theka niya kori ja ase kopal e
C43: Jodi free cashflow e nei tahole initial investment ta capex a dibo na? - ho
C44: EP kivhabe ber korbo?
